Workbook

Sheet Master
A1: Main
B2: Brand | C2: Generic | D2: Economics | E2: Indication | F2: MOA
B3: Androgel
B4: Kaletra
B5: Niaspan
B6: Rinvoq, fka ABT-494 | C6: upadacitinib | D6: 1 | E6: Rheumatoid Arthritis | F6: JAK
B7: Survanta
B8: Synagis | D8: AZN
B9: Tricor
B10: Venetoclax, ABT-199
B11: Zemplar
B12: ABT-267 | C12: ombitasvir
B13: ABT-450 | C13: paritaprevir
B14: Restasis (cyclosporine) | C14: Dry Eye | G14: Eyedrop
B15: Orilissa (elagolix) | C15: Uterine Fibroids | F15: NBIX | G15: Oral
B16: Viekira (paritaprevir, ombitasvir) | C16: HCV | F16: 1 | G16: Oral
B17: Durysta (bimatoprost) | C17: Glaucoma | G17: Eyedrop
C21: atrasentan | D21: KDNY | E21: DN
B22: ABT-179 | C22: modimelanotide | E22: AKI | F22: MCR/alpha-MSH
B23: ABT-126 | E23: Alzheimer's | F23: alpha7
B24: ABT-165 | E24: Oncology | F24: VEGF/DLL4
B25: ABT-122 | E25: RA | F25: TNF/IL-17A
B28: ABBV-916 | C28: Alzheimer's | D28: discontinued | E28: aBeta-pE3 mab

Sheet Main
B2: Name | C2: Indication | D2: Approved | E2: MOA | F2: Economics | G2: Administration | H2: IP | J2: Price | K2: 208
B3: Humira (adalimumab) | C3: RA, PSO, CD, UC, PsA, HS, Uveitis, AS | D3: 37621 | E3: TNF | F3: 1 | G3: Subcutaneous | H3: 2024 | J3: Shares | K3: 1771 | L3: Q225
B4: Botox (onabotulinumtoxinA) | C4: Aesthetics, Cervical Dystonia | D4: 33581 | E4: Botulinim | F4: 1 | G4: Subcutaneous | H4: Unclear | J4: MC | K4: =+K3*K2 -> 368368
B5: Imbruvica (ibrutinib) | C5: CLL, GvHD, WM | D5: 41591 | E5: BTK C481 | F5: JNJ | G5: Oral | H5: 46566 | J5: Cash | K5: 6777 | L5: Q225
B6: Skyrizi (risankizumab) | C6: Psoriasis, PsA, Crohn's, UC | D6: 43578 | E6: IL-23 | F6: BI? | G6: Subcutaneous | H6: Biologic | J6: Debt | K6: 70481 | L6: Q225
B7: Rinvoq (upadacitinib) | C7: RA, axSpA, AD, PsA, Crohn's, UC | D7: 44636 | E7: JAK | F7: 1 | G7: Oral | H7: 2030+ | J7: EV | K7: =+K4-K5+K6 -> 432072
B8: Venclexta (venetoclax) | C8: CLL, AML | D8: 42471 | E8: BCL-2 | F8: Roche | G8: Oral | H8: 2030-2033
B9: Lupron Depot (leuprolide) | C9: CRPC | D9: 32534 | F9: 100%? Takeda? | G9: IM
B10: Synthroid (levothyroxine) | C10: Hypothyroidism | D10: 37461 | F10: US only | G10: Oral
B11: Creon | C11: Pancreatic Insufficiency | F11: US only | G11: Oral
B12: Duodopa (carbidopa/levodopa) | C12: Parkinson's Disease | J12: CEO: Robert Michael succeeded Richard Gonzalez.
B13: Qulipta (atogepant) | C13: Migraine | E13: CGRP | F13: 1 | G13: Oral | J13: CFO: Robert A. Michael
B14: Elahere (mirvetuximab soravtansine) | C14: Ovarian Cancer | E14: FRalpha ADC | G14: IV | J14: SVP Discovery: Jonathon Sedgwick
B15: Emrelis (telisotuzumab vedotin) | C15: NSCLC | E15: cMet ADC | G15: IV | J15: Hematology: Mariana Cota Stirner
B16: Vuity (pilocarpine) | C16: Presbyopia | G16: Eyedrop | J16: Ophthalmology: Michael Robinson
B17: Epkinly (epcoritamab) | C17: DLBCL | D17: 45065 | E17: CD3xCD20 | F17: GMAB | G17: IV | J17: CSO: Roopal Thakkar
B18: Juvederm, Volux XC, Voluma XC | C18: Jawline Aesthetics, Temple Hollowing | E18: Dermal HA Filler | J18: Aesthetics: Sara Sangha
B19: Vyalev (foscarbidopa/foslevodopa) | C19: Parkinson's Disease | D19: CRL, approved in EU | E19: Dopamine | F19: 1 | J19: Immunology: Andrew Anisfeld
B20: Vraylar (cariprazine) | C20: Schizophrenia, Bipolar | G20: Oral
D21: Phase
B22: ABBV-400 (telisotuzumab adizutecan) | C22: mCRC, NSCLC, GEA | D22: II | E22: cMet ADC (different ADC) | J22: Acquisitions
B23: tavapadon | C23: Parkinson's Disease | D23: Filing | E23: D1/D5 partial agonist | G23: Oral | J23: Alpine
B24: emraclidine | C24: Schizophrenia | D24: II | E24: M4 PAM | G24: Oral | J24: Allergan
B25: BoNTE (AGN-151586) | C25: Glabellar Lines | D25: III | J25: Capstan
B26: ABBV-383 (etentamig) | C26: Multiple Myeloma | D26: III | E26: BCMA/CD3
B27: ABBV-RGX-314 | C27: AMD, DR | D27: III | E27: VEGF mab gene therapy | F27: RGNX | G27: intravitreal
B28: ABT-981 (lutikizumab) | C28: HS,UC (was OA) | D28: III | E28: IL-1a/1b | F28: 1 | J28: Early Stage Collaborations
B29: ABBV-157 | C29: Psoriasis | D29: II | E29: RORgammaT | F29: 1 | J29: ADARx Pharmaceuticals - siRNA
B30: ABBV-105 | C30: SLE | D30: II | E30: BTK | F30: 1
B31: elsubrutinib ABBV-599 (-105+Rinvoq) | C31: SLE | D31: II | E31: BTK+JAK | F31: 1
B32: ABBV-101 | D32: I | E32: BTK
B33: ABBV-382 | D33: II | E33: alpha4beta7 | F33: 1
B34: ABBV-668 | C34: Autoimmune | D34: II | E34: RIPK1 | F34: 1
B35: ALPN-101 | C35: SLE | D35: II | E35: CD28/ICOS | F35: ALPN
B36: ABBV-0805 | C36: Parkinson's Disease | D36: I | E36: alpha-synuclein | F36: 1
B37: ABBV-1088 | C37: Parkinson's Disease | D37: I | E37: PINK1 | F37: 1
B38: ABBV-8736 | C38: IBD | D38: I | E38: TREM1 mab | F38: 1
B39: ABBV-181 (budigalimab) | C39: Oncology | D39: II | E39: PD-1 | F39: 1
B40: ABBV-151 (livmoniplimab) | C40: Oncology | D40: II | E40: GARP-TGF-B1
B41: ABBV-113 (NX-13) | C41: UC/Crohn's | E41: NLRX1 agonist | F41: Acquired Landos
B42: FG-M701 | C42: IBD | E42: TL1A mab | F42: FutureGen
B43: CEL383 | D43: I | E43: TREM1 mab | F43: Acquired Celsius
B44: pivekimab sunirine | C44: AML, BPDCN | D44: II | E44: CD123 ADC
B45: ABBV-552 | C45: Alzheimer's | D45: II | E45: SV2A
B46: ALIA-1758 | C46: Alzheimer's | D46: II | E46: 3pE-Abeta mab with BBB crossing | F46: acquired Aliada
B47: ABBV-932 | C47: Bipolar, GAD | D47: I | E47: D3 | F47: Gedeon Richter
B48: razpipadon (CVL-871) | C48: Dementia Apathy | D48: II | E48: D1/D5 partial agonist
B49: CVL-354 (icalcaprant) | C49: Depression | D49: I | E49: KOR
B50: darigabat | C50: Panic Disorder, Focal Epilepsy | D50: II | E50: GABA-A receptor | F50: 1
B51: AL002 | C51: Alzheimer's | D51: II | E51: TREM2 | F51: Alector
B52: elezanumab | C52: Stroke, SCI | D52: II | E52: RGMa
B53: ABBV-CLS-7262 (fosigotifator) | C53: ALS, VWM | D53: II | E53: eIF2B | F53: Calico
B54: CUG-252 | C54: SLE | D54: I | E54: IL-2 | F54: Cugene
B55: OpSCF | C55: Atopic Dermatitis | D55: II | E55: SCF248 mab | F55: Opsidio
B56: CLF065 | C56: IBD/SBS | D56: II | E56: GLP2R agonist | F56: Scripps
B57: ABT-414 | C57: GBM
B58: ABBV-969 | C58: mCRPC | D58: I | E58: PSMA/STEAP1 ADC
B59: ISB 2001 | C59: Multiple Myeloma | D59: I | E59: CD3xBCMAxCD38 | F59: Ichnos Glenmark - 750m upfront!
B60: ABBV-323 (ravagalimab) | D60: I | G60: SC
B61: ABBV-CLS-484 | D61: I | E61: PTPN2 | F61: Calico
B62: ABBV-CLS-616 | D62: I
B63: GUB014295 | C63: T2D | D63: I | E63: amylin analog
B64: ABBV-787 | C64: AML | D64: I
B65: ABBV-706 | C65: SCLC, NENs | D65: I | E65: SEZ6 ADC
B66: DJS-002 | C66: IPF | D66: I | E66: LPAR1 mab | F66: 1
B67: ABT-888 (veliparib) | C67: Ovarian Cancer | D67: II | E67: PARP | F67: 1
B68: AGN-193408 | C68: Ocular Hypertension, Glaucoma | D68: II | E68: Prostaglandin | F68: 1
B69: ABBV-514 | D69: I | E69: CCR8 mab | F69: 1
B70: ABBV-142
B71: ABBV-141
B72: ABBV-950 | D72: I | E72: Botulinim
B73: ABBV-525 | D73: I | E73: MALT1 inhibitor | F73: 1
B74: ABBV-722 | D74: I
B75: CPTX-2309 | E75: CD19 CART
B76: ABBV-453 | C76: R/R MM | D76: I | E76: Bcl-2 | F76: 1
B77: ABBV-903 | D77: I
B78: ABBV-291 | C78: NHL | D78: I
B79: ABBV-319 | C79: Oncology | D79: I | E79: CD19/ADC | F79: 1
B80: SIM0500 | C80: Multiple Myeloma | D80: I | E80: BCMA/GPRC5D/CD3 | F80: Simcere
B81: TTX-030 | C81: Pancreatic Cancer | D81: I
B82: ABBV-303 | C82: Oncology | D82: I | E82: c-Met | F82: Dragonfly
B83: ABT-700 | C83: Cancer
B84: ABT-767
E86: 1/13/25: Licenses Simcere's trispecific for multiple myeloma
E87: 1/13/25: ABBV-RGX-314 phase 3 trial for DR planned
E88: 1/9/25: conference presentation
E89: 1/7/25: CoolSculpting promotion
E90: 1/3/25: Q424 results date.
E91: 12/13/24: Nimble Therapeutics acquisition, oral peptide IL23R inhibitor. $200m upfront.
E92: 12/11/24: closes Aliada Therapeutics acquisition, ALIA-1758 for Alzheimer's.
E93: 12/9/24: Epkinly DLBCL data
E94: 12/9/24: TEMPO-2 results for Alzheimer's
E95: 12/8/24: CLL patient advocacy
E96: 12/7/24: Epkinly FL data
E97: 11/25/24: investor conference
... E125: ABT-333, dasabuvir

Sheet Model
A1: Main
C2: Q103 | D2: Q203 | E2: Q303 | F2: Q403 | G2: Q104 | H2: Q204 | I2: Q304 | J2: Q404 | K2: Q105 | L2: Q205 | M2: Q305 | N2: Q405 | O2: Q106 | P2: Q206 | Q2: Q306 | R2: Q406 | S2: Q107 | T2: Q207 | U2: Q307 | V2: Q407 | W2: Q108 | X2: Q208 | Y2: Q308 | Z2: Q408 | AA2: Q109 | AB2: Q209 | AC2: Q309 | AD2: Q409 | AE2: Q110 | AF2: Q210 | AG2: Q310 | AH2: Q410 | AI2: Q111 | AJ2: Q211 | AK2: Q311 | AL2: Q411 | AM2: Q112 | AN2: Q212 | AO2: Q312 | AP2: Q412 | AQ2: Q113 | AR2: Q213 | AS2: Q313 | AT2: Q413 | AU2: Q114 | AV2: Q214 | AW2: Q314 | AX2: Q414 | AY2: Q115 | AZ2: Q215 | BA2: Q315 | BB2: Q415 | BC2: Q116 | BD2: Q216 | BE2: Q316 | BF2: Q416 | BG2: Q117 | BH2: Q217 | BI2: Q317 | BJ2: Q417 | BK2: Q118 | BL2: Q218 | BM2: Q318 | BN2: Q418 | BO2: Q119 | BP2: Q219 | BQ2: Q319 | BR2: Q419 | BS2: Q120 | BT2: Q220 | BU2: Q320 | BV2: Q420 | BW2: Q121 | BX2: Q221 | BY2: Q321 | BZ2: Q421 | CA2: Q122 | CB2: Q222 | CC2: Q322 | CD2: Q422 | CE2: Q123 | CF2: Q223 | CG2: Q323 | CH2: Q423 | CI2: Q124 | CJ2: Q224 | CK2: Q324 | CL2: Q424 | CM2: Q125 | CN2: Q225 | CO2: Q325 | CP2: Q425 | CQ2: Q126 | CR2: Q226 | CS2: Q326 | CT2: Q426 | CV2: 2010 | CW2: 2011 | CX2: 2012 | CY2: 2013 | CZ2: =+CY2+1 -> 2014 | DA2: =+CZ2+1 -> 2015 | DB2: =+DA2+1 -> 2016 | DC2: =+DB2+1 -> 2017 | DD2: =+DC2+1 -> 2018 | DE2: =+DD2+1 -> 2019 | DF2: =+DE2+1 -> 2020 | DG2: =+DF2+1 -> 2021 | ... DU2: =+DT2+1 -> 2035
B3: Combined Immunology | AW3: =+AW5+AW8+AW13 -> 3255 | AX3: =+AX5+AX8+AX13 -> 3363 | AY3: =+AY5+AY8+AY13 -> 3111 | AZ3: =+AZ5+AZ8+AZ13 -> 3537 | BA3: =+BA5+BA8+BA13 -> 3647 | BB3: =+BB5+BB8+BB13 -> 3717 | BC3: =+BC5+BC8+BC13 -> 3577 | BD3: =+BD5+BD8+BD13 -> 4149 | ... CT3: =+CT5+CT8+CT13 -> 10478 | CX3: =+CX5+CX8+CX13 -> 9265 | CY3: =+CY5+CY8+CY13 -> 10659 | CZ3: =+CZ5+CZ8+CZ13 -> 12543 | DA3: =+DA5+DA8+DA13 -> 14012 | DB3: =+DB5+DB8+DB13 -> 16078 | DC3: =+DC5+DC8+DC13 -> 18427 | DD3: =+DD5+DD8+DD13 -> 19936 | DE3: =+DE5+DE8+DE13 -> 19571 | ... DP3: =+DP5+DP8+DP13 -> 33788.939
B5: Humira | C5: 30 | D5: 60 | E5: 80 | F5: 110 | G5: 149 | H5: =579-I5-G5 -> 203 | I5: 227 | J5: 273 | K5: 282 | L5: 321 | M5: =1400-N5-L5-K5 -> 356 | N5: 441 | O5: 392 | P5: =1424-Q5-O5 -> 491 | Q5: 541 | R5: 620 | S5: 571 | T5: 735 | U5: 803 | V5: 954 | W5: 878 | X5: 1089 | Y5: 1204 | Z5: 1351 | AA5: =2335-AB5 -> 1024 | AB5: 1311 | AC5: 1491 | AD5: 1662 | AE5: 1397 | AF5: 1593 | AG5: 1679 | AH5: 1879 | AI5: 1646 | AJ5: 1997 | AK5: =7932-AL5-AI5-AJ5 -> 2111 | AL5: 2178 | AM5: 1934 | AN5: 2326 | AO5: 2325 | AP5: 2681 | AQ5: 2244 | AR5: 2606 | AS5: 2770 | AT5: 3039 | AU5: 2637 | AV5: 3288 | AW5: 3255 | AX5: 3363 | AY5: 3111 | AZ5: 3537 | BA5: 3647 | BB5: 3717 | BC5: 3577 | BD5: 4149 | BE5: 4060 | BF5: 4292 | BG5: 4118 | BH5: 4716 | BI5: 4701 | BJ5: 4892 | BK5: 4709 | BL5: 5185 | BM5: 5124 | BN5: 4918 | BO5: 4446 | BP5: 4870 | BQ5: 4936 | BR5: 4917 | BS5: 4703 | BT5: 4837 | BU5: 5140 | BV5: 5152 | BW5: 4867 | BX5: 5068 | BY5: 5425 | BZ5: 5334 | CA5: 4736 | CB5: 5363 | CC5: 5559 | CD5: 5579 | CE5: 3541 | CF5: 4012 | CG5: 3547 | CH5: 3304 | CI5: 2270 | CJ5: 2814 | CK5: 2227 | CL5: 1682 | CM5: 1121 | CN5: 1180 | CO5: 993 | CP5: 1246 | CQ5: =+CM5*0.9 -> 1008.9 | CR5: =+CN5*0.9 -> 1062 | CS5: =+CO5*0.9 -> 893.7 | CT5: =+CP5*0.9 -> 1121.4 | CX5: 9265 | CY5: 10659 | CZ5: 12543 | DA5: 14012 | DB5: 16078 | DC5: 18427 | DD5: =SUM(BK5:BN5) -> 19936 | DE5: =SUM(BO5:BR5) -> 19169 | DF5: =SUM(BS5:BV5) -> 19832 | DG5: =SUM(BW5:BZ5) -> 20694 | DH5: =SUM(CA5:CD5) -> 21237 | DI5: =SUM(CE5:CH5) -> 14404 | DJ5: =SUM(CI5:CL5) -> 8993 | DK5: =SUM(CM5:CP5) -> 4540 | DL5: =+DK5*0.8 -> 3632 | DM5: =+DL5*0.8 -> 2905.6 | DN5: =+DM5*0.5 -> 1452.8 | DO5: =+DN5*0.5 -> 726.4 | DP5: =+DO5*0.5 -> 363.2 | DQ5: =+DP5*0.5 -> 181.6 | DR5: =+DQ5*0.5 -> 90.8 | DS5: =+DR5*0.5 -> 45.4 | DT5: =+DS5*0.5 -> 22.7 | DU5: =+DT5*0.5 -> 11.35
B6: Botox Total | AQ6: - | BG6: 0 | BH6: 0 | BI6: 0 | BJ6: 0 | BK6: 0 | BL6: 0 | BM6: 0 | BN6: 0 | BO6: 0 | BP6: 0 | BQ6: 0 | BR6: 0 | BS6: 0 | BT6: 523 | BU6: 916 | BV6: 1,060 | BW6: 1,009 | BX6: 1,187 | BY6: 1,190 | BZ6: 1,297 | CA6: 1,255 | CB6: 1,373 | CC6: 1,336 | CD6: 1,370 | CE6: 1,378 | CF6: 1,433 | CG6: 1,368 | CH6: 1,494 | CI6: 1,381 | CJ6: 1,543 | CK6: 1,519 | CL6: 1,496 | CM6: 1,422 | CN6: 1,620 | CO6: 1,584 | CP6: 1,707 | CX6: =SUM(BE6:BH6) -> 0 | CY6: =SUM(BF6:BI6) -> 0 | CZ6: =SUM(BG6:BJ6) -> 0 | DA6: =SUM(BH6:BK6) -> 0 | DB6: =SUM(BI6:BL6) -> 0 | DC6: =SUM(BJ6:BM6) -> 0 | DD6: =SUM(BK6:BN6) -> 0 | DE6: =SUM(BO6:BR6) -> 0 | DF6: 2,499 | DG6: 4,683 | DH6: 5,488 | DI6: 5,673 | DJ6: 6,003
B7: Imbruvica | AQ7: - | AZ7: 107 | BA7: 304 | BB7: 343 | BC7: 381 | BD7: 439 | BE7: 501 | BF7: 511 | BG7: 551 | BH7: 626 | BI7: 688 | BJ7: 708 | BK7: 762 | BL7: 850 | BM7: 972 | BN7: 1006 | BO7: 1022 | BP7: 1099 | BQ7: 1257 | BR7: 1296 | BS7: 1232 | BT7: 1288 | BU7: 1370 | BV7: 1424 | BW7: 1268 | BX7: 1381 | BY7: 1374 | BZ7: 1385 | CA7: 1173 | CB7: 1145 | CC7: 1135 | CD7: 1115 | CE7: 878 | CF7: 907 | CG7: 908 | CH7: 903 | CI7: 838 | CJ7: 833 | CK7: 828 | CL7: 848 | CM7: =+CI7*0.95 -> 796.1 | CN7: 754 | CO7: =+CK7*0.95 -> 786.6 | CP7: 671 | CQ7: =+CM7*0.9 -> 716.49 | CR7: =+CN7*0.9 -> 678.6 | CS7: =+CO7*0.9 -> 707.94 | CT7: =+CP7*0.9 -> 603.9 | CX7: 0 | CY7: 0 | CZ7: 0 | DA7: 754 | DB7: 1832 | DC7: 2573 | DD7: =SUM(BK7:BN7) -> 3590 | DE7: =SUM(BO7:BR7) -> 4674 | DF7: =SUM(BS7:BV7) -> 5314 | DG7: =SUM(BW7:BZ7) -> 5408 | DH7: =SUM(CA7:CD7) -> 4568 | DI7: =SUM(CE7:CH7) -> 3596 | DJ7: =SUM(CI7:CL7) -> 3347 | DK7: =SUM(CM7:CP7) -> 3007.7 | DL7: =+DK7*0.9 -> 2706.93 | DM7: =+DL7*0.9 -> 2436.237 | DN7: =+DM7*0.9 -> 2192.6133 | DO7: =+DN7*0.9 -> 1973.352 | DP7: =+DO7*0.9 -> 1776.0168 | DQ7: =+DP7*0.9 -> 1598.4151 | DR7: =+DQ7*0.9 -> 1438.5736 | DS7: =+DR7*0.9 -> 1294.7162 | ... DU7: =+DT7*0.9 -> 1048.7201
B8: Skyrizi | BP8: 48 | BQ8: 91 | BR8: 216 | BS8: 300 | BT8: 330 | BU8: 435 | BV8: 525 | BW8: 574 | BX8: 674 | BY8: 796 | BZ8: 895 | CA8: 940 | CB8: 1252 | CC8: 1397 | CD8: 1576 | CE8: 1360 | CF8: 1883 | CG8: 2126 | CH8: 2394 | CI8: 2008 | CJ8: 2727 | CK8: 3205 | CL8: 3778 | CM8: 3425 | CN8: 4423 | CO8: 4708 | CP8: 5006 | CQ8: =+CM8*1.3 -> 4452.5 | CR8: =+CN8*1.3 -> 5749.9 | CS8: =+CO8*1.3 -> 6120.4 | CT8: =+CP8*1.3 -> 6507.8 | CX8: =SUM(BE8:BH8) -> 0 | CY8: =SUM(BF8:BI8) -> 0 | CZ8: =SUM(BG8:BJ8) -> 0 | DA8: =SUM(BH8:BK8) -> 0 | DB8: =SUM(BI8:BL8) -> 0 | DC8: =SUM(BJ8:BM8) -> 0 | DD8: =SUM(BK8:BN8) -> 0 | DE8: =SUM(BO8:BR8) -> 355 | DF8: =SUM(BS8:BV8) -> 1590 | DG8: =SUM(BW8:BZ8) -> 2939 | DH8: =SUM(CA8:CD8) -> 5165 | DI8: =SUM(CE8:CH8) -> 7763 | DJ8: =SUM(CI8:CL8) -> 11718 | DK8: =SUM(CM8:CP8) -> 17562 | DL8: =+DK8*1.03 -> 18088.86 | DM8: =+DL8*1.03 -> 18631.526 | DN8: =+DM8*1.03 -> 19190.472 | DO8: =+DN8*1.03 -> 19766.186 | DP8: =+DO8*1.03 -> 20359.171 | DQ8: =+DP8*1.03 -> 20969.946 | DR8: =+DQ8*1.03 -> 21599.045 | DS8: =+DR8*1.03 -> 22247.016 | ... DU8: =+DT8*1.03 -> 23601.859
B9: Botox Cosmetic | AQ9: - | BG9: 0 | BH9: 0 | BI9: 0 | BJ9: 0 | BK9: 0 | BL9: 0 | BM9: 0 | BN9: 0 | BO9: 0 | BP9: 0 | BQ9: 0 | BR9: 0 | BS9: 0 | BT9: 226 | BU9: 393 | BV9: 493 | BW9: 477 | BX9: 584 | BY9: 545 | BZ9: 626 | CA9: 641 | CB9: 695 | CC9: 637 | CD9: 642 | CE9: 659 | CF9: 685 | CG9: 620 | CH9: =2682-CG9-CF9-CE9 -> 718 | CI9: 633 | CJ9: 729 | CK9: 671 | CL9: 687 | CM9: 556 | CN9: 692 | CO9: =+CK9*0.97 -> 650.87 | CP9: 717 | CQ9: =+CM9*1.1 -> 611.6 | CR9: =+CN9*1.1 -> 761.2 | CS9: =+CO9*1.1 -> 715.957 | CT9: =+CP9*1.1 -> 788.7 | CX9: =SUM(BE9:BH9) -> 0 | CY9: =SUM(BF9:BI9) -> 0 | CZ9: =SUM(BG9:BJ9) -> 0 | DA9: =SUM(BH9:BK9) -> 0 | DB9: =SUM(BI9:BL9) -> 0 | DC9: =SUM(BJ9:BM9) -> 0 | DD9: =SUM(BK9:BN9) -> 0 | DE9: =SUM(BO9:BR9) -> 0 | DF9: =SUM(BS9:BV9) -> 1112 | DG9: =SUM(BW9:BZ9) -> 2232 | DH9: =SUM(CA9:CD9) -> 2615 | DI9: =SUM(CE9:CH9) -> 2682 | DJ9: =SUM(CI9:CL9) -> 2720 | DK9: =SUM(CM9:CP9) -> 2615.87 | DL9: =+DK9*1.05 -> 2746.6635 | DM9: =+DL9*1.05 -> 2883.9967 | DN9: =+DM9*1.05 -> 3028.1965 | DO9: =+DN9*1.05 -> 3179.6063 | DP9: =+DO9*1.05 -> 3338.5867 | DQ9: =+DP9*1.05 -> 3505.516 | DR9: =+DQ9*1.05 -> 3680.7918 | DS9: =+DR9*1.05 -> 3864.8314 | ... DU9: =+DT9*1.05 -> 4260.9766
B10: Botox Therapeutic | AQ10: - | BG10: 0 | BH10: 0 | BI10: 0 | BJ10: 0 | BK10: 0 | BL10: 0 | BM10: 0 | BN10: 0 | BO10: 0 | BP10: 0 | BQ10: 0 | BR10: 0 | BS10: 0 | BT10: 297 | BU10: 523 | BV10: 567 | BW10: 532 | BX10: 603 | BY10: 645 | BZ10: 671 | CA10: 614 | CB10: 678 | CC10: 699 | CD10: 728 | CE10: 719 | CF10: 748 | CG10: 748 | CH10: =2991-CG10-CF10-CE10 -> 776 | CI10: 748 | CJ10: 814 | CK10: 848 | CL10: 873 | CM10: 866 | CN10: 928 | CO10: =+CK10*1.1 -> 932.8 | CP10: 990 | CQ10: =+CM10*1.1 -> 952.6 | CR10: =+CN10*1.1 -> 1020.8 | CS10: =+CO10*1.1 -> 1026.08 | CT10: =+CP10*1.1 -> 1089 | CX10: =SUM(BE10:BH10) -> 0 | CY10: =SUM(BF10:BI10) -> 0 | CZ10: =SUM(BG10:BJ10) -> 0 | DA10: =SUM(BH10:BK10) -> 0 | DB10: =SUM(BI10:BL10) -> 0 | DC10: =SUM(BJ10:BM10) -> 0 | DD10: =SUM(BK10:BN10) -> 0 | DE10: =SUM(BO10:BR10) -> 0 | DF10: =SUM(BS10:BV10) -> 1387 | DG10: =SUM(BW10:BZ10) -> 2451 | DH10: =SUM(CA10:CD10) -> 2719 | DI10: =SUM(CE10:CH10) -> 2991 | DJ10: =SUM(CI10:CL10) -> 3283 | DK10: =SUM(CM10:CP10) -> 3716.8 | DL10: =+DK10*1.05 -> 3902.64 | DM10: =+DL10*1.05 -> 4097.772 | DN10: =+DM10*1.05 -> 4302.6606 | DO10: =+DN10*1.05 -> 4517.7936 | DP10: =+DO10*1.05 -> 4743.6833 | DQ10: =+DP10*1.05 -> 4980.8675 | DR10: =+DQ10*1.05 -> 5229.9109 | DS10: =+DR10*1.05 -> 5491.4064 | ... DU10: =+DT10*1.05 -> 6054.2755
B11: BonTE | CX11: 0 | CY11: 0 | CZ11: 0 | DA11: 0 | DB11: 0 | DC11: 0 | DD11: 0 | DE11: 0 | DL11: 500 | DM11: 1000 | DN11: 1250 | DO11: 1500 | DP11: 1750 | DQ11: 2000 | DR11: 2200 | DS11: 2400 | DT11: 2600 | DU11: 2800
B12: Venclexta | BM12: 96 | BN12: 124 | BO12: 151 | BP12: 169 | BQ12: 221 | BR12: 251 | BS12: 317 | BT12: 303 | BU12: 352 | BV12: 365 | BW12: 405 | BX12: 435 | BY12: 492 | BZ12: 488 | CA12: 473 | CB12: 505 | CC12: 515 | CD12: 516 | CE12: 538 | CF12: 571 | CG12: 590 | CH12: 589 | CI12: 614 | CJ12: 637 | CK12: 677 | CL12: 655 | CM12: 665 | CN12: 691 | CO12: 726 | CP12: 710 | CQ12: =+CM12*1.1 -> 731.5 | CR12: =+CN12*1.1 -> 760.1 | CS12: =+CO12*1.1 -> 798.6 | CT12: =+CP12*1.1 -> 781 | CX12: 0 | CY12: 0 | CZ12: 0 | DD12: =SUM(BK12:BN12) -> 220 | DE12: =SUM(BO12:BR12) -> 792 | DF12: =SUM(BS12:BV12) -> 1337 | DG12: =SUM(BW12:BZ12) -> 1820 | DH12: =SUM(CA12:CD12) -> 2009 | DI12: =SUM(CE12:CH12) -> 2288 | DJ12: =SUM(CI12:CL12) -> 2583 | DK12: =SUM(CM12:CP12) -> 2792 | DL12: =+DK12*1.03 -> 2875.76 | DM12: =+DL12*1.03 -> 2962.0328 | DN12: =+DM12*1.03 -> 3050.8938 | DO12: =+DN12*1.03 -> 3142.4206 | DP12: =+DO12*0.1 -> 314.24206 | DQ12: =+DP12*0.1 -> 31.424206 | DR12: =+DQ12*0.1 -> 3.1424206 | DS12: =+DR12*0.1 -> 0.31424206 | DT12: =+DS12*0.1 -> 0.031424206 | DU12: =+DT12*0.1 -> 0.0031424206
B13: Rinvoq | BQ13: 14 | BR13: 33 | BS13: 86 | BT13: 149 | BU13: 215 | BV13: 281 | BW13: 303 | BX13: 378 | BY13: 453 | BZ13: 517 | CA13: 465 | CB13: 592 | CC13: 695 | CD13: 770 | CE13: 686 | CF13: 918 | CG13: 1110 | CH13: 1255 | CI13: 1093 | CJ13: 1430 | CK13: 1614 | CL13: 1834 | CM13: 1718 | CN13: 2028 | CO13: 2184 | CP13: 2374 | CQ13: =+CM13*1.2 -> 2061.6 | CR13: =+CN13*1.2 -> 2433.6 | CS13: =+CO13*1.2 -> 2620.8 | CT13: =+CP13*1.2 -> 2848.8 | CX13: =SUM(BE13:BH13) -> 0 | CY13: =SUM(BF13:BI13) -> 0 | CZ13: =SUM(BG13:BJ13) -> 0 | DA13: =SUM(BH13:BK13) -> 0 | DB13: =SUM(BI13:BL13) -> 0 | DC13: =SUM(BJ13:BM13) -> 0 | DD13: =SUM(BK13:BN13) -> 0 | DE13: =SUM(BO13:BR13) -> 47 | DF13: =SUM(BS13:BV13) -> 731 | DG13: =SUM(BW13:BZ13) -> 1651 | DH13: =SUM(CA13:CD13) -> 2522 | DI13: =SUM(CE13:CH13) -> 3969 | DJ13: =SUM(CI13:CL13) -> 5971 | DK13: =SUM(CM13:CP13) -> 8304 | DL13: =+DK13*1.2 -> 9964.8 | DM13: =+DL13*1.2 -> 11957.76 | DN13: =+DM13*1.03 -> 12316.493 | DO13: =+DN13*1.03 -> 12685.988 | DP13: =+DO13*1.03 -> 13066.567 | DQ13: =+DP13*0.1 -> 1306.6567 | DR13: =+DQ13*0.1 -> 130.66567 | DS13: =+DR13*0.1 -> 13.066567 | DT13: =+DS13*0.1 -> 1.3066567 | DU13: =+DT13*0.1 -> 0.13066567
B14: Vraylar | AQ14: - | BG14: 0 | BH14: 0 | BI14: 0 | BJ14: 0 | BK14: 0 | BL14: 0 | BM14: 0 | BN14: 0 | BO14: 0 | BP14: 0 | BQ14: 0 | BR14: 0 | BS14: 0 | BT14: 192 | BU14: 358 | BV14: 401 | BW14: 346 | BX14: 432 | BY14: 461 | BZ14: 489 | CA14: 427 | CB14: 492 | CC14: 554 | CD14: 565 | CE14: 561 | CF14: 658 | CG14: 751 | CH14: 789 | CI14: 694 | CJ14: 774 | CK14: 875 | CL14: 924 | CM14: 765 | CN14: 900 | CO14: 934 | CP14: 1022 | CQ14: =+CM14*1.2 -> 918 | CR14: =+CN14*1.2 -> 1080 | CS14: =+CO14*1.2 -> 1120.8 | CT14: =+CP14*1.2 -> 1226.4 | CX14: =SUM(BE14:BH14) -> 0 | CY14: =SUM(BF14:BI14) -> 0 | CZ14: =SUM(BG14:BJ14) -> 0 | DA14: =SUM(BH14:BK14) -> 0 | DB14: =SUM(BI14:BL14) -> 0 | DC14: =SUM(BJ14:BM14) -> 0 | DD14: =SUM(BK14:BN14) -> 0 | DE14: =SUM(BO14:BR14) -> 0 | DF14: =SUM(BS14:BV14) -> 951 | DG14: =SUM(BW14:BZ14) -> 1728 | DH14: =SUM(CA14:CD14) -> 2038 | DI14: =SUM(CE14:CH14) -> 2759 | DJ14: =SUM(CI14:CL14) -> 3267 | DK14: =SUM(CM14:CP14) -> 3621 | DL14: =+DK14*1.03 -> 3729.63 | DM14: =+DL14*1.03 -> 3841.5189 | DN14: =+DM14*1.03 -> 3956.7645 | DO14: =+DN14*1.03 -> 4075.4674 | DP14: =+DO14*0.1 -> 407.54674 | DQ14: =+DP14*0.1 -> 40.754674 | DR14: =+DQ14*0.1 -> 4.0754674 | DS14: =+DR14*0.1 -> 0.40754674 | DT14: =+DS14*0.1 -> 0.040754674 | DU14: =+DT14*0.1 -> 0.0040754674
B15: Juvederm | AQ15: - | BG15: 0 | BH15: 0 | BI15: 0 | BJ15: 0 | BK15: 0 | BL15: 0 | BM15: 0 | BN15: 0 | BO15: 0 | BP15: 0 | BQ15: 0 | BR15: 0 | BS15: 0 | BT15: 113 | BU15: 274 | BV15: 331 | BW15: 321 | BX15: 428 | BY15: 354 | BZ15: 252 | CA15: 410 | CB15: 344 | CC15: 352 | CD15: 322 | CE15: 355 | CF15: 368 | CG15: 321 | CH15: 334 | CI15: 297 | CJ15: 343 | CK15: 258 | CL15: 279 | CM15: 231 | CN15: 260 | CO15: 253 | CP15: 249 | CQ15: =+CM15 -> 231 | CR15: =+CN15 -> 260 | CS15: =+CO15 -> 253 | CT15: =+CP15 -> 249 | CX15: =SUM(BE15:BH15) -> 0 | CY15: =SUM(BF15:BI15) -> 0 | CZ15: =SUM(BG15:BJ15) -> 0 | DA15: =SUM(BH15:BK15) -> 0 | DB15: =SUM(BI15:BL15) -> 0 | DC15: =SUM(BJ15:BM15) -> 0 | DD15: =SUM(BK15:BN15) -> 0 | DE15: =SUM(BO15:BR15) -> 0 | DF15: =SUM(BS15:BV15) -> 718 | DG15: =SUM(BW15:BZ15) -> 1355 | DH15: =SUM(CA15:CD15) -> 1428 | DI15: =SUM(CE15:CH15) -> 1378 | DJ15: =SUM(CI15:CL15) -> 1177 | DK15: =SUM(CM15:CP15) -> 993 | DL15: =+DK15*1.05 -> 1042.65 | DM15: =+DL15*1.05 -> 1094.7825 | DN15: =+DM15*1.05 -> 1149.5216 | DO15: =+DN15*1.05 -> 1206.9977 | DP15: =+DO15*1.05 -> 1267.3476 | DQ15: =+DP15*1.05 -> 1330.715 | DR15: =+DQ15*1.05 -> 1397.2507 | DS15: =+DR15*1.05 -> 1467.1133 | ... DU15: =+DT15*1.05 -> 1617.4924
B16: Mavyret | AQ16: 0 | BG16: 0 | BH16: 0 | BI16: 276 | BJ16: 510 | BK16: 919 | BL16: 973 | BM16: 839 | BN16: 819 | BO16: 790 | BP16: 780 | BQ16: 695 | BR16: 628 | BS16: 559 | BT16: 376 | BU16: 414 | BV16: 481 | BW16: 415 | BX16: 442 | BY16: 426 | BZ16: 427 | CA16: 380 | CB16: 398 | CC16: 383 | CD16: 380 | CE16: 364 | CF16: 387 | CG16: 370 | CH16: 309 | CI16: 349 | CJ16: 369 | CK16: 302 | CL16: 291 | CM16: 306 | CN16: 375 | CO16: 312 | CP16: 324 | CQ16: =+CM16 -> 306 | CR16: =+CN16 -> 375 | CS16: =+CO16 -> 312 | CT16: =+CP16 -> 324 | DD16: =SUM(BK16:BN16) -> 3550 | DE16: =SUM(BO16:BR16) -> 2893 | DF16: =SUM(BS16:BV16) -> 1830 | DG16: =SUM(BW16:BZ16) -> 1710 | DH16: =SUM(CA16:CD16) -> 1541 | DI16: =SUM(CE16:CH16) -> 1430 | DJ16: =SUM(CI16:CL16) -> 1311 | DK16: =SUM(CM16:CP16) -> 1317 | DL16: =+DK16*0.7 -> 921.9 | DM16: =+DL16*0.7 -> 645.33 | DN16: =+DM16*0.7 -> 451.731 | DO16: =+DN16*0.7 -> 316.2117 | DP16: =+DO16*0.7 -> 221.34819 | DQ16: =+DP16*0.7 -> 154.94373 | DR16: =+DQ16*0.7 -> 108.46061 | DS16: =+DR16*0.7 -> 75.922429 | ... DU16: =+DT16*0.7 -> 37.20199
B17: Other Aesthetics | AQ17: - | BG17: 0 | BH17: 0 | BI17: 0 | BJ17: 0 | BK17: 0 | BL17: 0 | BM17: 0 | BN17: 0 | BO17: 0 | BP17: 0 | BQ17: 0 | BR17: 0 | BS17: 0 | BT17: 142 | BU17: 300 | BV17: 318 | BW17: 343 | BX17: 422 | BY17: 352 | BZ17: 349 | CA17: 323 | CB17: 332 | CC17: 312 | CD17: 323 | CE17: 286 | CF17: 331 | CG17: 298 | CH17: 319 | CI17: 319 | CJ17: 318 | CK17: 310 | CL17: 332 | CM17: 315 | CN17: 327 | CO17: 303 | CP17: 320 | CQ17: =+CM17 -> 315 | CR17: =+CN17 -> 327 | CS17: =+CO17 -> 303 | CT17: =+CP17 -> 320 | DD17: =SUM(BK17:BN17) -> 0 | DE17: =SUM(BO17:BR17) -> 0 | DF17: =SUM(BS17:BV17) -> 760 | DG17: =SUM(BW17:BZ17) -> 1466 | DH17: =SUM(CA17:CD17) -> 1290 | DI17: =SUM(CE17:CH17) -> 1234 | DJ17: =SUM(CI17:CL17) -> 1279 | DK17: =SUM(CM17:CP17) -> 1265 | DL17: =+DK17*0.9 -> 1138.5 | DM17: =+DL17*0.9 -> 1024.65 | DN17: =+DM17*0.9 -> 922.185 | DO17: =+DN17*0.9 -> 829.9665 | DP17: =+DO17*0.9 -> 746.96985 | DQ17: =+DP17*0.9 -> 672.27287 | DR17: =+DQ17*0.9 -> 605.04558 | DS17: =+DR17*0.9 -> 544.54102 | ... DU17: =+DT17*0.9 -> 441.07823
B18: Creon | AM18: 146 | AN18: 162 | AO18: 163 | AP18: 188 | AQ18: 90 | AR18: 106 | AS18: 101 | AT18: 115 | AU18: 107 | AV18: 110 | AW18: 148 | AX18: 151 | AY18: 127 | AZ18: 159 | BA18: 161 | BB18: 185 | BC18: 150 | BD18: 180 | BE18: 187 | BF18: 213 | BG18: 185 | BH18: 196 | BI18: 215 | BJ18: 235 | BK18: 209 | BL18: 219 | BM18: 239 | BN18: 261 | BO18: 227 | BP18: 257 | BQ18: 265 | BR18: 292 | BS18: 276 | BT18: 252 | BU18: 282 | BV18: 304 | BW18: 274 | BX18: 280 | BY18: 310 | BZ18: 327 | CA18: 287 | CB18: 318 | CC18: 336 | CD18: 337 | CE18: 305 | CF18: 282 | CG18: 305 | CH18: 376 | CI18: 285 | CJ18: 372 | CK18: 338 | CL18: 388 | CM18: 355 | CN18: 404 | CO18: 368 | CP18: 385 | CQ18: =+CM18 -> 355 | CR18: =+CN18 -> 404 | CS18: =+CO18 -> 368 | CT18: =+CP18 -> 385 | CX18: 353 | CY18: 412 | CZ18: 516 | DA18: 632 | DB18: 730 | DC18: 831 | DD18: =SUM(BK18:BN18) -> 928 | DE18: =SUM(BO18:BR18) -> 1041 | DF18: =SUM(BS18:BV18) -> 1114 | DG18: =SUM(BW18:BZ18) -> 1191 | DH18: =SUM(CA18:CD18) -> 1278 | DI18: =SUM(CE18:CH18) -> 1268 | DJ18: =SUM(CI18:CL18) -> 1383 | DK18: =SUM(CM18:CP18) -> 1512 | DL18: =+DK18*1.03 -> 1557.36 | DM18: =+DL18*1.03 -> 1604.0808 | DN18: =+DM18*1.03 -> 1652.2032 | DO18: =+DN18*1.03 -> 1701.7693 | DP18: =+DO18*1.03 -> 1752.8224 | DQ18: =+DP18*1.03 -> 1805.4071 | DR18: =+DQ18*1.03 -> 1859.5693 | DS18: =+DR18*1.03 -> 1915.3564 | ... DU18: =+DT18*1.03 -> 2032.0016
B19: Other Eye Care | BG19: 0 | BH19: 0 | BI19: 0 | BJ19: 0 | BK19: 0 | BL19: 0 | BM19: 0 | BN19: 0 | BO19: 0 | BP19: 0 | BQ19: 0 | BR19: 0 | BS19: 0 | BT19: 128 | BU19: 269 | BV19: 296 | BW19: 276 | BX19: 301 | BY19: 286 | BZ19: 306 | CA19: 278 | CB19: 217 | CC19: =287-CC32 -> 181 | CD19: =283-CD32 -> 71 | CE19: 200 | CF19: 215 | CG19: 207 | CH19: 181 | CI19: 200 | CJ19: 225 | CK19: 207 | CL19: 215 | CM19: 217 | CN19: 250 | CO19: 248 | CP19: 294 | CQ19: =+CM19 -> 217 | CR19: =+CN19 -> 250 | CS19: =+CO19 -> 248 | CT19: =+CP19 -> 294 | DD19: =SUM(BK19:BN19) -> 0 | DE19: =SUM(BO19:BR19) -> 0 | DF19: =SUM(BS19:BV19) -> 693 | DG19: =SUM(BW19:BZ19) -> 1169 | DH19: =SUM(CA19:CD19) -> 747 | DI19: =SUM(CE19:CH19) -> 803 | DJ19: =SUM(CI19:CL19) -> 847 | DK19: =SUM(CM19:CP19) -> 1009 | DL19: =+DK19*0.9 -> 908.1 | DM19: =+DL19*0.9 -> 817.29 | DN19: =+DM19*0.9 -> 735.561 | DO19: =+DN19*0.9 -> 662.0049 | DP19: =+DO19*0.9 -> 595.80441 | DQ19: =+DP19*0.9 -> 536.22397 | DR19: =+DQ19*0.9 -> 482.60157 | DS19: =+DR19*0.9 -> 434.34141 | ... DU19: =+DT19*0.9 -> 351.81655
B20: Restasis | BG20: 0 | BH20: 0 | BI20: 0 | BJ20: 0 | BK20: 0 | BL20: 0 | BM20: 0 | BN20: 0 | BO20: 0 | BP20: 0 | BQ20: 0 | BR20: 0 | BS20: 0 | BT20: 144 | BU20: 299 | BV20: 344 | BW20: 280 | BX20: 327 | BY20: 319 | BZ20: 364 | CA20: 246 | CB20: 168 | CC20: 142 | CD20: 110 | CE20: 92 | CF20: 99 | CG20: 117 | CH20: 128 | CI20: 57 | CJ20: 32 | CK20: 21 | CL20: 114 | DD20: =SUM(BK20:BN20) -> 0 | DE20: =SUM(BO20:BR20) -> 0 | DF20: =SUM(BS20:BV20) -> 787 | DG20: =SUM(BW20:BZ20) -> 1290 | DH20: =SUM(CA20:CD20) -> 666 | DI20: =SUM(CE20:CH20) -> 436 | DJ20: =SUM(CI20:CL20) -> 224 | DK20: =SUM(CM20:CP20) -> 0 | DL20: =+DK20*0.9 -> 0 | DM20: =+DL20*0.9 -> 0 | DN20: =+DM20*0.9 -> 0 | DO20: =+DN20*0.9 -> 0 | DP20: =+DO20*0.9 -> 0 | DQ20: =+DP20*0.9 -> 0 | DR20: =+DQ20*0.9 -> 0 | DS20: =+DR20*0.9 -> 0 | ... DU20: =+DT20*0.9 -> 0
B21: Linzess | BG21: 0 | BH21: 0 | BI21: 0 | BJ21: 0 | BK21: 0 | BL21: 0 | BM21: 0 | BN21: 0 | BO21: 0 | BP21: 0 | BQ21: 0 | BR21: 0 | BS21: 0 | BT21: 133 | BU21: 248 | BV21: 286 | BW21: 222 | BX21: 268 | BY21: 261 | BZ21: 287 | CA21: 240 | CB21: 255 | CC21: 271 | CD21: 269 | CE21: 259 | CF21: 278 | CG21: 288 | CH21: 283 | CI21: 266 | CJ21: 221 | CK21: 234 | CL21: 233 | CM21: 148 | CN21: 258 | CO21: 326 | CP21: 175 | CQ21: =+CP21-5 -> 170 | CR21: =+CQ21-5 -> 165 | CS21: =+CR21-5 -> 160 | CT21: =+CS21-5 -> 155 | DD21: =SUM(BK21:BN21) -> 0 | DE21: =SUM(BO21:BR21) -> 0 | DF21: =SUM(BS21:BV21) -> 667 | DG21: =SUM(BW21:BZ21) -> 1038 | DH21: =SUM(CA21:CD21) -> 1035 | DI21: =SUM(CE21:CH21) -> 1108 | DJ21: =SUM(CI21:CL21) -> 954 | DK21: =SUM(CM21:CP21) -> 907 | DL21: =+DK21*0.5 -> 453.5 | DM21: =+DL21*0.5 -> 226.75 | DN21: =+DM21*0.5 -> 113.375 | DO21: =+DN21*0.5 -> 56.6875 | DP21: =+DO21*0.5 -> 28.34375 | DQ21: =+DP21*0.5 -> 14.171875 | DR21: =+DQ21*0.5 -> 7.0859375 | DS21: =+DR21*0.5 -> 3.5429688 | ... DU21: =+DT21*0.5 -> 0.88574219
B22: Other CNS | BG22: 0 | BH22: 0 | BI22: 0 | BJ22: 0 | BK22: 0 | BL22: 0 | BM22: 0 | BN22: 0 | BO22: 0 | BP22: 0 | BQ22: 0 | BR22: 0 | BS22: 0 | BT22: 105 | BU22: 207 | BV22: 227 | BW22: 160 | BX22: 171 | BY22: 171 | BZ22: 183 | CA22: 177 | CB22: 150 | CC22: 87 | CD22: 61 | CE22: 79 | CF22: 70 | CG22: 61 | CH22: 66 | CI22: 74 | CJ22: 80 | CK22: 84 | CL22: 100 | CM22: =+CI22 -> 74 | CN22: 55 | CO22: 46 | CP22: 47 | CQ22: =+CP22 -> 47 | CR22: =+CQ22 -> 47 | CS22: =+CR22 -> 47 | CT22: =+CS22 -> 47 | DD22: =SUM(BK22:BN22) -> 0 | DE22: =SUM(BO22:BR22) -> 0 | DF22: =SUM(BS22:BV22) -> 539 | DG22: =SUM(BW22:BZ22) -> 685 | DH22: =SUM(CA22:CD22) -> 475 | DI22: =SUM(CE22:CH22) -> 276 | DJ22: =SUM(CI22:CL22) -> 338 | DK22: =SUM(CM22:CP22) -> 222 | DL22: =+DK22*0.9 -> 199.8 | DM22: =+DL22*0.9 -> 179.82 | DN22: =+DM22*0.9 -> 161.838 | DO22: =+DN22*0.9 -> 145.6542 | DP22: =+DO22*0.9 -> 131.08878 | DQ22: =+DP22*0.9 -> 117.9799 | DR22: =+DQ22*0.9 -> 106.18191 | DS22: =+DR22*0.9 -> 95.563721 | ... DU22: =+DT22*0.9 -> 77.406614
B23: Lumigan/Ganfort | BG23: 0 | BH23: 0 | BI23: 0 | BJ23: 0 | BK23: 0 | BL23: 0 | BM23: 0 | BN23: 0 | BO23: 0 | BP23: 0 | BQ23: 0 | BR23: 0 | BS23: 0 | BT23: 76 | BU23: 149 | BV23: 153 | BW23: 143 | BX23: 149 | BY23: 138 | BZ23: 149 | CA23: 140 | CB23: 130 | CC23: 121 | CD23: 123 | CE23: 130 | CF23: 119 | CG23: 91 | CH23: 92 | CI23: 91 | CJ23: 103 | CK23: 116 | CL23: 119 | CM23: 106 | CN23: 103 | CO23: 97 | CP23: 104 | CQ23: =+CM23 -> 106 | CR23: =+CN23 -> 103 | CS23: =+CO23 -> 97 | CT23: =+CP23 -> 104 | DD23: =SUM(BK23:BN23) -> 0 | DE23: =SUM(BO23:BR23) -> 0 | DF23: =SUM(BS23:BV23) -> 378 | DG23: =SUM(BW23:BZ23) -> 579 | DH23: =SUM(CA23:CD23) -> 514 | DI23: =SUM(CE23:CH23) -> 432 | DJ23: =SUM(CI23:CL23) -> 429 | DK23: =SUM(CM23:CP23) -> 410 | DL23: =+DK23*0.9 -> 369 | DM23: =+DL23*0.9 -> 332.1 | DN23: =+DM23*0.9 -> 298.89 | DO23: =+DN23*0.9 -> 269.001 | DP23: =+DO23*0.9 -> 242.1009 | DQ23: =+DP23*0.9 -> 217.89081 | DR23: =+DQ23*0.9 -> 196.10173 | DS23: =+DR23*0.9 -> 176.49156 | ... DU23: =+DT23*0.9 -> 142.95816
B24: Ubrelvy | BG24: 0 | BH24: 0 | BI24: 0 | BJ24: 0 | BK24: 0 | BL24: 0 | BM24: 0 | BN24: 0 | BO24: 0 | BP24: 0 | BQ24: 0 | BR24: 0 | BS24: 0 | BT24: 22 | BU24: 38 | BV24: 65 | BW24: 81 | BX24: 126 | BY24: 162 | BZ24: 183 | CA24: 138 | CB24: 185 | CC24: 160 | CD24: 197 | CE24: 152 | CF24: 196 | CG24: 233 | CH24: 234 | CI24: 203 | CJ24: 231 | CK24: 269 | CL24: 303 | CM24: 240 | CN24: 338 | CO24: 354 | CP24: 339 | CQ24: =+CP24+5 -> 344 | CR24: =+CQ24+5 -> 349 | CS24: =+CR24+5 -> 354 | CT24: =+CS24+5 -> 359 | DD24: =SUM(BK24:BN24) -> 0 | DE24: =SUM(BO24:BR24) -> 0 | DF24: =SUM(BS24:BV24) -> 125 | DG24: =SUM(BW24:BZ24) -> 552 | DH24: =SUM(CA24:CD24) -> 680 | DI24: =SUM(CE24:CH24) -> 815 | DJ24: =SUM(CI24:CL24) -> 1006 | DK24: =SUM(CM24:CP24) -> 1271 | DL24: =+DK24*1.2 -> 1525.2 | DM24: =+DL24*1.1 -> 1677.72 | DN24: =+DM24*1.1 -> 1845.492 | DO24: =+DN24*1.03 -> 1900.8568 | DP24: =+DO24*0.1 -> 190.08568 | DQ24: =+DP24*0.1 -> 19.008568 | DR24: =+DQ24*0.1 -> 1.9008568 | DS24: =+DR24*0.1 -> 0.19008568 | DT24: =+DS24*0.1 -> 0.019008568 | DU24: =+DT24*0.1 -> 0.0019008568
B25: Duodopa | AO25: 37 | AQ25: 39 | AR25: 44 | AS25: 46 | AT25: 49 | AU25: 52 | AV25: 56 | AW25: 56 | AX25: 56 | AY25: 53 | AZ25: 55 | BA25: 61 | BB25: 62 | BC25: 68 | BD25: 73 | BE25: 74 | BF25: 78 | BG25: 80 | BH25: 81 | BI25: 94 | BJ25: 100 | BK25: 103 | BL25: 108 | BM25: 106 | BN25: 113 | BO25: 111 | BP25: 115 | BQ25: 117 | BR25: 118 | BS25: 124 | BT25: 118 | BU25: 123 | BV25: 129 | BW25: 129 | BX25: 127 | BY25: 127 | BZ25: 128 | CA25: 121 | CB25: 120 | CC25: 110 | CD25: 107 | CE25: 118 | CF25: 117 | CG25: 118 | CH25: 115 | CI25: 115 | CJ25: 113 | CK25: 111 | CL25: 108 | CM25: 96 | CN25: 97 | CO25: 96 | CP25: 92 | CQ25: =+CM25 -> 96 | CR25: =+CN25 -> 97 | CS25: =+CO25 -> 96 | CT25: =+CP25 -> 92 | CX25: 149 | CY25: 178 | CZ25: 220 | DA25: 231 | DB25: 293 | DC25: 355 | DD25: =SUM(BK25:BN25) -> 430 | DE25: =SUM(BO25:BR25) -> 461 | DF25: =SUM(BS25:BV25) -> 494 | DG25: =SUM(BW25:BZ25) -> 511 | DH25: =SUM(CA25:CD25) -> 458 | DI25: =SUM(CE25:CH25) -> 468 | DJ25: =SUM(CI25:CL25) -> 447 | DK25: =SUM(CM25:CP25) -> 381 | DL25: =+DK25*0.9 -> 342.9 | DM25: =+DL25*0.9 -> 308.61 | DN25: =+DM25*0.9 -> 277.749 | DO25: =+DN25*0.9 -> 249.9741 | DP25: =+DO25*0.9 -> 224.97669 | DQ25: =+DP25*0.9 -> 202.47902 | DR25: =+DQ25*0.9 -> 182.23112 | DS25: =+DR25*0.9 -> 164.00801 | ... DU25: =+DT25*0.9 -> 132.84649
B26: Alphagan/Combigan | BG26: 0 | BH26: 0 | BI26: 0 | BJ26: 0 | BK26: 0 | BL26: 0 | BM26: 0 | BN26: 0 | BO26: 0 | BP26: 0 | BQ26: 0 | BR26: 0 | BS26: 0 | BT26: 69 | BU26: 123 | BV26: 134 | BW26: 118 | BX26: 142 | BY26: 128 | BZ26: 141 | CA26: 107 | CB26: 92 | CC26: 73 | CD26: 74 | CE26: 71 | CF26: 65 | CG26: 70 | CH26: 66 | CI26: 59 | CJ26: 49 | CK26: 62 | CL26: 78 | CM26: 60 | CN26: 36 | CO26: 47 | CP26: 54 | CQ26: =+CM26 -> 60 | CR26: =+CN26 -> 36 | CS26: =+CO26 -> 47 | CT26: =+CP26 -> 54 | DD26: =SUM(BK26:BN26) -> 0 | DE26: =SUM(BO26:BR26) -> 0 | DF26: =SUM(BS26:BV26) -> 326 | DG26: =SUM(BW26:BZ26) -> 529 | DH26: =SUM(CA26:CD26) -> 346 | DI26: =SUM(CE26:CH26) -> 272 | DJ26: =SUM(CI26:CL26) -> 248 | DK26: =SUM(CM26:CP26) -> 197 | DL26: =+DK26*0.9 -> 177.3 | DM26: =+DL26*0.9 -> 159.57 | DN26: =+DM26*0.9 -> 143.613 | DO26: =+DN26*0.9 -> 129.2517 | DP26: =+DO26*0.9 -> 116.32653 | DQ26: =+DP26*0.9 -> 104.69388 | DR26: =+DQ26*0.9 -> 94.224489 | DS26: =+DR26*0.9 -> 84.80204 | ... DU26: =+DT26*0.9 -> 68.689653
B27: Qulipta | BG27: 0 | BH27: 0 | BI27: 0 | BJ27: 0 | BK27: 0 | BL27: 0 | BM27: 0 | BN27: 0 | BO27: 0 | BP27: 0 | BQ27: 0 | BR27: 0 | BS27: 0 | BT27: 0 | BU27: 0 | BV27: 0 | BW27: 0 | BX27: 0 | BY27: 0 | BZ27: 0 | CA27: 11 | CB27: 33 | CC27: 62 | CD27: 52 | CE27: 66 | CF27: 96 | CG27: 132 | CH27: 114 | CI27: 131 | CJ27: 150 | CK27: 176 | CL27: 201 | CM27: 193 | CN27: 267 | CO27: 288 | CP27: 288 | CQ27: =+CP27+5 -> 293 | CR27: =+CQ27+5 -> 298 | CS27: =+CR27+5 -> 303 | CT27: =+CS27+5 -> 308 | DD27: =SUM(BK27:BN27) -> 0 | DE27: =SUM(BO27:BR27) -> 0 | DF27: =SUM(BS27:BV27) -> 0 | DG27: =SUM(BW27:BZ27) -> 0 | DH27: =SUM(CA27:CD27) -> 158 | DI27: =SUM(CE27:CH27) -> 408 | DJ27: =SUM(CI27:CL27) -> 658 | DK27: =SUM(CM27:CP27) -> 1036 | DL27: =+DK27*1.2 -> 1243.2 | DM27: =+DL27*1.1 -> 1367.52 | DN27: =+DM27*1.1 -> 1504.272 | DO27: =+DN27*1.03 -> 1549.4002 | DP27: =+DO27*0.1 -> 154.94002 | DQ27: =+DP27*0.1 -> 15.494002 | DR27: =+DQ27*0.1 -> 1.5494002 | DS27: =+DR27*0.1 -> 0.15494002 | DT27: =+DS27*0.1 -> 0.015494002 | DU27: =+DT27*0.1 -> 0.0015494002
B28: Elahere | CI28: 64 | CJ28: 128 | CK28: 139 | CL28: 148 | CM28: 179 | CN28: 159 | CO28: 170 | CP28: 182 | CQ28: =+CP28+5 -> 187 | CR28: =+CQ28+5 -> 192 | CS28: =+CR28+5 -> 197 | CT28: =+CS28+5 -> 202 | DJ28: =SUM(CI28:CL28) -> 479 | DK28: =SUM(CM28:CP28) -> 690 | DL28: =+DK28*1.1 -> 759 | DM28: =+DL28*1.1 -> 834.9 | DN28: =+DM28*1.1 -> 918.39 | DO28: =+DN28*1.1 -> 1010.229 | DP28: =+DO28*1.1 -> 1111.2519 | DQ28: =+DP28*1.1 -> 1222.3771 | DR28: =+DQ28*1.1 -> 1344.6148 | DS28: =+DR28*1.1 -> 1479.0763 | ... DU28: =+DT28*1.1 -> 1789.6823
B29: teliso-V | DK29: =SUM(CM29:CP29) -> 0 | DL29: 500 | DM29: 800 | DN29: 1200 | DO29: 1500 | DP29: 1800 | DQ29: 2000 | DR29: 2200 | DS29: 2400 | DT29: 2600 | DU29: 2800
B30: Other Oncology | CP30: 20 | CQ30: =+CP30 -> 20 | CR30: =+CQ30 -> 20 | CS30: =+CR30 -> 20 | CT30: =+CS30 -> 20
B31: Epkinly | CG31: 14 | CH31: 17 | CI31: 27 | CJ31: 36 | CK31: 43 | CL31: 40 | CM31: 51 | CN31: 70 | CO31: 69 | CP31: 81 | CQ31: =+CP31+3 -> 84 | CR31: =+CQ31+3 -> 87 | CS31: =+CR31+3 -> 90 | CT31: =+CS31+3 -> 93 | DI31: =SUM(CE31:CH31) -> 31 | DJ31: =SUM(CI31:CL31) -> 146 | DK31: =SUM(CM31:CP31) -> 271 | DL31: =+DK31*1.4 -> 379.4 | DM31: =+DL31*1.3 -> 493.22 | DN31: =+DM31*1.2 -> 591.864 | DO31: =+DN31*1.2 -> 710.2368 | DP31: =+DO31*1.1 -> 781.26048 | DQ31: =+DP31*1.05 -> 820.3235 | DR31: =+DQ31*1.05 -> 861.33968 | DS31: =+DR31*1.05 -> 904.40666 | DT31: =+DS31*1.05 -> 949.627 | DU31: =+DT31*1.05 -> 997.10835
B32: Ozurdex | CB32: 110 | CC32: 106 | CD32: =428-CC32-CB32-CA32 -> 212 | CE32: 115 | CF32: 119 | CG32: 120 | CH32: 118 | CI32: 131 | CJ32: 124 | CK32: 119 | CL32: 120 | CM32: 123 | CN32: 125 | CO32: 117 | CP32: 128 | CQ32: =+CM32 -> 123 | CR32: =+CN32 -> 125 | CS32: =+CO32 -> 117 | CT32: =+CP32 -> 128 | DH32: =SUM(CA32:CD32) -> 428 | DI32: =SUM(CE32:CH32) -> 472 | DJ32: =SUM(CI32:CL32) -> 494 | DK32: =SUM(CM32:CP32) -> 493 | DL32: =+DK32 -> 493 | DM32: =+DL32 -> 493 | DN32: =+DM32 -> 493 | DO32: =+DN32 -> 493 | DP32: =+DO32 -> 493 | DQ32: =+DP32 -> 493 | DR32: =+DQ32 -> 493 | DS32: =+DR32 -> 493 | ... DU32: =+DT32 -> 493
B33: tavapadon | DK33: =SUM(CM33:CP33) -> 0 | DL33: 200 | DM33: 300 | DN33: =+DM33*1.01 -> 303 | DO33: =+DN33*1.01 -> 306.03 | DP33: =+DO33*1.01 -> 309.0903 | DQ33: =+DP33*1.01 -> 312.1812 | DR33: =+DQ33*1.01 -> 315.30302 | DS33: =+DR33*1.01 -> 318.45605 | DT33: =+DS33*1.01 -> 321.64061 | DU33: =+DT33*0.1 -> 32.164061
B34: Vyalev | CM34: 63 | CN34: 98 | CO34: 138 | CP34: 183 | CQ34: =+CP34+10 -> 193 | CR34: =+CQ34+10 -> 203 | CS34: =+CR34+10 -> 213 | CT34: =+CS34+10 -> 223 | DK34: =SUM(CM34:CP34) -> 482 | DL34: 150 | DM34: 300 | DN34: 450 | DO34: 600 | DP34: 700 | DQ34: 800 | DR34: 900 | DS34: 1000 | DT34: =+DS34 -> 1000 | DU34: =+DT34 -> 1000
B35: Lo Loestrin | BG35: 0 | BH35: 0 | BI35: 0 | BJ35: 0 | BK35: 0 | BL35: 0 | BM35: 0 | BN35: 0 | BO35: 0 | BP35: 0 | BQ35: 0 | BR35: 0 | BS35: 0 | BT35: 80 | DD35: =SUM(BK35:BN35) -> 0 | DE35: =SUM(BO35:BR35) -> 0 | DF35: =SUM(BS35:BV35) -> 80
B36: Orilissa | BG36: 0 | BH36: 0 | BI36: 0 | BJ36: 0 | BK36: 0 | BL36: 0 | BM36: 0 | BN36: 0 | BO36: 0 | BP36: 19 | BQ36: 27 | BR36: 34 | BS36: 31 | BT36: 31 | DD36: =SUM(BK36:BN36) -> 0 | DE36: =SUM(BO36:BR36) -> 80 | DF36: =SUM(BS36:BV36) -> 62
B37: leuprolide | G37: 50 | H37: 43 | I37: 50 | J37: 54 | K37: 52 | L37: 57 | M37: =219-N37-L37-K37 -> 56 | N37: 54 | O37: 53 | P37: 58 | Q37: =168-P37-O37 -> 57 | R37: 61
B38: lansoprazole | G38: 37 | H38: 30 | I38: 35 | J38: 41 | K38: 36 | L38: 37 | M38: =154-L38-K38-N38 -> 40 | N38: 41 | O38: 40 | P38: 44 | Q38: =127-P38-O38 -> 43 | R38: 46
B39: Prevacid | G39: 700 | H39: 706 | I39: 711 | J39: 475 | K39: 590 | L39: 337 | M39: =2501-L39-K39-N39 -> 942 | N39: 632 | O39: 616 | P39: 663 | Q39: =1891-P39-O39 -> 612 | R39: 709
B40: Lupron | G40: 180 | H40: 182 | I40: 202 | J40: 206 | K40: 171 | L40: 174 | M40: =699-L40-K40-N40 -> 181 | N40: 173 | O40: 168 | P40: 159 | Q40: =499-P40-O40 -> 172 | R40: 164 | W40: =218-X40 -> 64 | X40: 154 | Y40: 221 | Z40: 213 | AA40: =390-AB40 -> 193 | AB40: 197 | AC40: 195 | AD40: 215 | AE40: 172 | AF40: 187 | AG40: 189 | AH40: 200 | AI40: 184 | AJ40: 205 | AK40: =810-AJ40-AI40-AL40 -> 213 | AL40: 208 | AM40: 199 | AN40: 200 | AO40: 189 | AP40: 211 | AQ40: 181 | AR40: 199 | AS40: 196 | AT40: 209 | AU40: 189 | AV40: 186 | AW40: 196 | AX40: 207 | AY40: 192 | AZ40: 198 | BA40: 201 | BB40: 235 | BC40: 190 | BD40: 219 | BE40: 193 | BF40: 219 | BG40: 194 | BH40: 210 | BI40: 201 | BJ40: 224 | BK40: 219 | BL40: 223 | BM40: 214 | BN40: 236 | BO40: 229 | BP40: 209 | BQ40: 230 | BR40: 219 | BS40: 233 | BT40: 205 | CX40: 800 | CY40: 785 | CZ40: 778 | DA40: 826 | DB40: 821 | DC40: 829 | DD40: =SUM(BK40:BN40) -> 892 | DE40: =SUM(BO40:BR40) -> 887 | DF40: =SUM(BS40:BV40) -> 438
B41: Synthroid | G41: 180 | H41: 189 | I41: 165 | J41: 154 | K41: 136 | L41: 127 | M41: =554-L41-K41-N41 -> 135 | N41: 156 | O41: 126 | P41: 149 | Q41: =403-P41-O41 -> 128 | R41: 132 | S41: 129 | T41: 121 | U41: 130 | V41: 153 | W41: 115 | X41: 138 | Y41: 129 | Z41: 142 | AA41: =220-AB41 -> 104 | AB41: 116 | AC41: 134 | AD41: 148 | AE41: 123 | AF41: 129 | AG41: 143 | AH41: 160 | AI41: 145 | AJ41: 169 | AK41: =638-AJ41-AI41-AL41 -> 161 | AL41: 163 | AM41: 155 | AN41: 149 | AO41: 157 | AP41: 194 | AQ41: 119 | AR41: 153 | AS41: 161 | AT41: 189 | AU41: 157 | AV41: 166 | AW41: 200 | AX41: 186 | AY41: 186 | AZ41: 187 | BA41: 188 | BB41: 194 | BC41: 182 | BD41: 188 | BE41: 188 | BF41: 205 | BG41: 192 | BH41: 193 | BI41: 191 | BJ41: 205 | BK41: 182 | BL41: 193 | BM41: 192 | BN41: 209 | BO41: 182 | BP41: 203 | BQ41: 197 | BR41: 204 | BS41: 205 | BT41: 183 | CX41: 551 | CY41: 622 | CZ41: 709 | DA41: 755 | DB41: 763 | DC41: 781 | DD41: =SUM(BK41:BN41) -> 776 | DE41: =SUM(BO41:BR41) -> 786 | DF41: =SUM(BS41:BV41) -> 388
B42: Other Women's | BG42: 0 | BH42: 0 | BI42: 0 | BJ42: 0 | BK42: 0 | BL42: 0 | BM42: 0 | BN42: 0 | BO42: 0 | BP42: 0 | BQ42: 0 | BR42: 0 | BS42: 0 | BT42: 36 | DD42: =SUM(BK42:BN42) -> 0 | DE42: =SUM(BO42:BR42) -> 0 | DF42: =SUM(BS42:BV42) -> 36
B43: Synagis | AO43: 96 | AQ43: 345 | AR43: 70 | AS43: 98 | AT43: 314 | AU43: 354 | AV43: 74 | AW43: 109 | AX43: 298 | AY43: 335 | AZ43: 46 | BA43: 93 | BB43: 266 | BC43: 319 | BD43: 45 | BE43: 96 | BF43: 270 | BG43: 300 | BH43: 40 | BI43: 116 | BJ43: 282 | BK43: 321 | BL43: 44 | BM43: 97 | BN43: 264 | BO43: 287 | BP43: 38 | BQ43: 132 | BR43: 261 | BS43: 270 | CX43: 825 | CY43: 827 | CZ43: 835 | DA43: 740 | DB43: 730 | DC43: 738 | DD43: =SUM(BK43:BN43) -> 726 | DE43: =SUM(BO43:BR43) -> 718 | DF43: =SUM(BS43:BV43) -> 270
B44: Ultane | G44: 17 | H44: 193 | I44: 200 | J44: 211 | K44: 197 | L44: 226 | M44: =874-L44-K44-N44 -> 218 | N44: 233 | O44: 207 | P44: 189 | Q44: =604-P44-O44 -> 208 | R44: 195 | S44: 174 | T44: 197 | U44: 188 | V44: 200 | W44: 187 | X44: 202 | Y44: 200 | Z44: 198
B45: AndroGel | AM45: 241 | AN45: 284 | AO45: 287 | AP45: 373 | AQ45: 240 | AR45: 258 | AS45: 248 | AT45: 289 | AU45: 254 | AV45: 218 | AW45: 232 | AX45: 230 | AY45: 153 | AZ45: 170 | BA45: 177 | BB45: 194 | BC45: 156 | BD45: 171 | BE45: 174 | BF45: 174 | BG45: 136 | BH45: 154 | BI45: 147 | BJ45: 140 | BK45: 130 | BL45: 128 | BM45: 135 | BN45: 76 | BO45: 74 | BP45: 22 | BQ45: 53 | BR45: 23 | BS45: 8 | CY45: 1035 | CZ45: 934 | DA45: 694 | DB45: 675 | DC45: 577 | DD45: =SUM(BK45:BN45) -> 469 | DE45: =SUM(BO45:BR45) -> 172 | DF45: =SUM(BS45:BV45) -> 8
B46: Mobic | G46: 104 | H46: 104 | I46: 126 | J46: 258 | K46: 293 | L46: 322 | M46: =1232-N46-K46-L46 -> 311 | N46: 306
B47: Omnicef | G47: 75 | H47: 50 | I47: 50 | J47: 148 | K47: 135 | L47: 85 | M47: =495-N47-L47-K47 -> 86 | N47: 189 | O47: 143 | P47: 135 | Q47: =378-P47-O47 -> 100 | R47: 259 | S47: 161
B48: Biaxin | G48: 290 | H48: 286 | I48: 224 | J48: 383 | K48: 353 | L48: 254 | M48: =1065-N48-L48-K48 -> 177 | N48: 281 | O48: 249 | P48: 138 | Q48: =580-P48-O48 -> 193 | R48: 235 | S48: 224 | T48: 170 | U48: 131 | V48: 200 | W48: 222 | X48: 159 | Y48: 115 | Z48: 154
B49: Kaletra | G49: 200 | H49: 225 | I49: 224 | J49: 247 | K49: 238 | L49: 236 | M49: =1005-N49-L49-K49 -> 259 | N49: 272 | O49: 280 | P49: 294 | Q49: =839-P49-O49 -> 265 | R49: 159 | S49: 300 | T49: 315 | U49: 338 | V49: 371 | W49: 353 | X49: 355 | Y49: 387 | Z49: 378 | AA49: =635-AB49 -> 292 | AB49: 343 | AC49: 353 | AD49: 378 | AE49: 292 | AF49: 294 | AG49: 328 | AH49: 341 | AI49: 248 | AJ49: 336 | AK49: =1170-AJ49-AI49-AL49 -> 298 | AL49: 288 | AM49: 221 | AN49: 275 | AO49: 267 | AP49: 250 | AQ49: 219 | AR49: 278 | AS49: 237 | AT49: 228 | AU49: 195 | AV49: 216 | AW49: 256 | AX49: 203 | AY49: 180 | AZ49: 167 | BA49: 168 | BB49: 185 | BC49: 133 | BD49: 146 | BE49: 137 | BF49: 133 | BG49: 115 | BH49: 110 | BI49: 85 | BJ49: 113 | BK49: 73 | BL49: 91 | BM49: 88 | BN49: 84 | BO49: 78 | BP49: 77 | BQ49: 74 | BR49: 54 | BS49: 86 | CX49: 1013 | CY49: 962 | CZ49: 870 | DA49: 700 | DB49: 549 | DC49: 423 | DD49: =SUM(BK49:BN49) -> 336 | DE49: =SUM(BO49:BR49) -> 283 | DF49: =SUM(BS49:BV49) -> 86
B50: Depakote | G50: 225 | H50: 224 | I50: 262 | J50: 317 | K50: 217 | L50: 267 | M50: =1096-N50-L50-K50 -> 262 | N50: 350 | O50: 246 | P50: 339 | Q50: =904-P50-O50 -> 319 | R50: 405 | S50: 326 | T50: 404 | U50: 383 | V50: 461 | W50: 365 | X50: 414 | Y50: 387 | Z50: 268 | AA50: =232-AB50 -> 130 | AB50: 102 | AC50: 92 | AD50: 102
B51: Niaspan | S51: 142 | T51: 170 | U51: 167 | V51: 179 | W51: 176 | X51: 194 | Y51: 194 | Z51: 221 | AA51: =386-AB51 -> 178 | AB51: 208 | AC51: 215 | AD51: 254 | AE51: 205 | AF51: 211 | AG51: 225 | AH51: 286 | AI51: 226 | AJ51: 247 | AK51: =976-AJ51-AI51-AL51 -> 245 | AL51: 258 | AM51: 191 | AN51: 211 | AO51: 232 | AP51: 277 | AQ51: 186 | AR51: 232 | AS51: 201 | AT51: 31 | AU51: 47 | AV51: 21 | BG51: 0 | BH51: 0 | BI51: 0 | BJ51: 0 | BK51: 0 | BL51: 0 | BM51: 0 | BN51: 0 | BO51: 0 | BP51: 0 | BQ51: 0 | BR51: 0 | BS51: 0 | DD51: =SUM(BK51:BN51) -> 0 | DE51: =SUM(BO51:BR51) -> 0 | DF51: =SUM(BS51:BV51) -> 0
B52: Viekira | AX52: 48 | AY52: 231 | AZ52: 385 | BA52: 469 | BB52: 554 | BC52: 414 | BD52: 419 | BE52: 378 | BF52: 311 | BG52: 263 | BH52: 225 | BI52: 0 | BJ52: 0 | BK52: 0 | BL52: 0 | BM52: 23 | BN52: 43 | BO52: 25 | BP52: 4 | BQ52: 3 | BR52: 4 | BS52: 5 | CY52: 0 | CZ52: 48 | DA52: 1639 | DB52: 1522 | DD52: =SUM(BK52:BN52) -> 66 | DE52: =SUM(BO52:BR52) -> 36 | DF52: =SUM(BS52:BV52) -> 5
B53: TriCor | I53: 208 | J53: 227 | K53: 171 | L53: 219 | M53: =927-N53-L53-K53 -> 225 | N53: 312 | O53: 205 | P53: 266 | Q53: =722-P53-O53 -> 251 | R53: 326 | S53: 223 | T53: 302 | U53: 300 | V53: 392 | W53: 245 | X53: 307 | Y53: 334 | Z53: 455 | AA53: =588-AB53 -> 252 | AB53: 336 | AC53: 330 | AD53: 419 | AE53: 291 | AF53: 388 | AG53: 404 | AH53: 499 | AI53: 372 | AJ53: 419 | AK53: =1692-AJ53-AI53-AL53 -> 418 | AL53: 483 | AM53: 329 | AN53: 388 | AO53: 404 | AP53: 269 | AQ53: 128 | AR53: 107 | AS53: 39 | AT53: 29 | AU53: 23 | AV53: 17 | AW53: 63 | AX53: 104 | BG53: 0 | BH53: 0 | BI53: 0 | BJ53: 0 | BK53: 0 | BL53: 0 | BM53: 0 | BN53: 0 | BO53: 0 | BP53: 0 | BQ53: 0 | BR53: 0 | BS53: 0 | DD53: =SUM(BK53:BN53) -> 0 | DE53: =SUM(BO53:BR53) -> 0 | DF53: =SUM(BS53:BV53) -> 0
B54: Sevoflurane | AO54: 135 | AQ54: =274-AR54 -> 137 | AR54: 137 | AS54: 138 | AT54: 156 | AU54: 142 | AV54: 154 | AW54: 134 | AX54: 120 | AY54: 126 | AZ54: 118 | BA54: 122 | BB54: 108 | BC54: 111 | BD54: 114 | BE54: 102 | BF54: 101 | BG54: 107 | BH54: 104 | BI54: 100 | BJ54: 99 | BK54: 106 | BL54: 113 | BM54: 86 | BN54: 86 | BO54: 92 | BP54: 91 | BQ54: 84 | BR54: 81 | BS54: 79 | CY54: 568 | CZ54: 550 | DA54: 474 | DB54: 428 | DC54: 410 | DD54: =SUM(BK54:BN54) -> 391 | DE54: =SUM(BO54:BR54) -> 348 | DF54: =SUM(BS54:BV54) -> 79
B55: Zemplar | AO55: 91 | AQ55: 81 | AR55: 107 | AS55: 100 | AT55: 101 | AV55: 0 | BG55: 0 | BH55: 0 | BI55: 0 | BJ55: 0 | BK55: 0 | BL55: 0 | BM55: 0 | BN55: 0 | BO55: 0 | BP55: 0 | BQ55: 0 | BR55: 0 | BS55: 0 | DD55: =SUM(BK55:BN55) -> 0 | DE55: =SUM(BO55:BR55) -> 0 | DF55: =SUM(BS55:BV55) -> 0
B56: Main Products | C56: =SUM(C5:C55) -> 30 | D56: =SUM(D5:D55) -> 60 | E56: =SUM(E5:E55) -> 80 | F56: =SUM(F5:F55) -> 110 | G56: =SUM(G5:G55) -> 2207 | H56: =SUM(H5:H55) -> 2435 | I56: =SUM(I5:I55) -> 2684 | J56: =SUM(J5:J55) -> 2994 | ... BF56: =SUM(BF5:BF55) -> 6507 | BG56: 0 | BH56: 0 | BI56: 0 | BJ56: 0 | BK56: 0 | BL56: 0 | BM56: 0 | BN56: 0 | BO56: 0 | BP56: 0 | BQ56: 0 | BR56: 0 | BS56: 0 | DD56: =SUM(BK56:BN56) -> 0 | DE56: =SUM(BO56:BR56) -> 0 | DF56: =SUM(BS56:BV56) -> 0
B57: Other | AO57: 301 | AQ57: =+AQ58-AQ56 -> 320 | AR57: 395 | AS57: 323 | AT57: 362 | AU57: 406 | AV57: =4926-AV56 -> 420 | AW57: 370 | AX57: 486 | AY57: 346 | AZ57: 346 | BA57: 353 | BB57: 317 | BC57: 277 | BD57: 289 | BE57: 296 | BF57: 277 | BG57: =6538-SUM(BG5:BG56) -> 297 | BH57: =6944-SUM(BH5:BH56) -> 289 | BI57: =6995-SUM(BI5:BI56) -> 181 | BJ57: =7739-SUM(BJ5:BJ56) -> 231 | BK57: =7934-7733 -> 201 | BL57: 131 | BM57: 25 | BN57: =8305-8239 -> 66 | BO57: =7828-7714 -> 114 | BP57: 254 | BQ57: =8479-8396 -> 83 | BR57: =8704-8631 -> 73 | BS57: =8619-8514 -> 105 | BT57: =10425-9835 -> 590 | BU57: =12882-11512 -> 1370 | BV57: =13858-12276 -> 1582 | BW57: =12935-11534 -> 1401 | BX57: =13959-12738 -> 1221 | BY57: =14342-13225 -> 1117 | BZ57: =14886-13501 -> 1385 | CA57: =13538-12327 -> 1211 | CB57: =14583-13574 -> 1009 | CC57: 925 | CD57: 992 | CE57: 691 | CF57: 741 | CG57: 782 | CH57: =3035-CG57-CF57-CE57 -> 821 | CI57: 744 | CJ57: =14462-SUM(CJ5:CJ32) -> 810 | CK57: 726 | CL57: 752 | CM57: 563 | CN57: 605 | CO57: 629 | CP57: 617 | CQ57: 617 | DD57: =SUM(BK57:BN57) -> 423 | DE57: =SUM(BO57:BR57) -> 524 | DF57: =SUM(BS57:BV57) -> 3647 | DG57: =SUM(BW57:BZ57) -> 5124 | DH57: =SUM(CA57:CD57) -> 4137 | DI57: =SUM(CE57:CH57) -> 3035 | DJ57: =SUM(CI57:CL57) -> 3032 | DK57: =SUM(CM57:CP57) -> 2414 | DL57: =+DK57*0.9 -> 2172.6 | DM57: =+DL57*0.9 -> 1955.34 | DN57: =+DM57*0.9 -> 1759.806 | DO57: =+DN57*0.9 -> 1583.8254 | DP57: =+DO57*0.9 -> 1425.4429 | DQ57: =+DP57*0.9 -> 1282.8986 | DR57: =+DQ57*0.9 -> 1154.6087 | DS57: =+DR57*0.9 -> 1039.1478 | ... DU57: =+DT57*0.9 -> 841.70975
B58: Revenue | C58: =+C57+C56 -> 30 | D58: =+D57+D56 -> 60 | E58: =+E57+E56 -> 80 | F58: =+F57+F56 -> 110 | G58: =+G57+G56 -> 2207 | H58: =+H57+H56 -> 2435 | I58: =+I57+I56 -> 2684 | J58: =+J57+J56 -> 2994 | ... AP58: =+AP57+AP56 -> 4443 | AQ58: 4329 | AR58: =+AR56+AR57 -> 4692 | AS58: =+AS57+AS56 -> 4658 | AT58: =+AT57+AT56 -> 5111 | AU58: =+AU57+AU56 -> 4563 | AV58: =+AV57+AV56 -> 4926 | AW58: =+AW57+AW56 -> 5019 | AX58: =+AX57+AX56 -> 5452 | AY58: =+AY57+AY56 -> 5040 | AZ58: =+AZ57+AZ56 -> 5475 | ... BF58: =+BF57+BF56 -> 6784 | BG58: 6538 | BH58: 6944 | BI58: 6995 | BJ58: =SUM(BJ5:BJ57) -> 7739 | BK58: 7934 | BL58: =SUM(BL5:BL57) -> 8258 | BM58: =SUM(BM5:BM57) -> 8236 | BN58: =SUM(BN5:BN57) -> 8305 | BO58: =SUM(BO5:BO57) -> 7828 | BP58: =SUM(BP5:BP57) -> 8255 | BQ58: =SUM(BQ5:BQ57) -> 8479 | BR58: =SUM(BR5:BR57) -> 8704 | BS58: =SUM(BS5:BS57) -> 8619 | ... CT58: =SUM(CT5:CT57) -> 18324 | CV58: 15638 | CW58: 17444 | CX58: 18380 | CY58: 18790 | CZ58: 19960 | DA58: 22859 | DB58: 25638 | DC58: 28216 | DD58: =SUM(DD5:DD57) -> 32733 | DE58: =SUM(DE5:DE57) -> 33266 | DF58: =SUM(DF5:DF57) -> 45784 | DG58: =SUM(DG5:DG57) -> 56122 | DH58: =SUM(DH5:DH57) -> 58054 | DI58: =SUM(DI5:DI57) -> 54318 | DJ58: =SUM(DJ5:DJ57) -> 56334 | DK58: =SUM(DK5:DK57) -> 61029.37 | ... DU58: =SUM(DU5:DU57) -> 50633.365
B59: COGS | AQ59: 1153 | AR59: 1054 | AS59: 1092 | AT59: 1282 | AU59: 1100 | AV59: =1113-69-3-6 -> 1035 | AW59: 1094 | AX59: 1119 | AY59: 942 | AZ59: 916 | BA59: 1167 | BB59: 1475 | BC59: 1369 | BD59: 1405 | BE59: 1235 | BF59: 1287 | BG59: 1313 | BH59: 1231 | BI59: 1342 | BJ59: 1625 | BK59: 1572 | BL59: 1607 | BM59: 1509 | BN59: 1674 | BO59: 1303 | BP59: 1427 | BQ59: 1525 | BR59: 1605 | BS59: 1494 | BT59: 1796 | BU59: 2362 | BV59: 2523 | BW59: 2085 | BX59: 2479 | BY59: 2413 | BZ59: 2448 | CA59: 2103 | CB59: 2167 | CC59: 2167 | CD59: =+CD58-CD60 -> 2268.15 | CE59: 1931 | CF59: 2117 | CG59: 2301 | CH59: 2297 | CI59: 2108 | CJ59: 2135 | CK59: 2251 | CL59: 2453 | CM59: 2116 | CN59: 2413 | CO59: =+CO58-CO60 -> 2366.4405 | CP59: =+CP58-CP60 -> 2492.7 | DD59: =SUM(BK59:BN59) -> 6362 | DE59: =SUM(BO59:BR59) -> 5860 | DF59: =SUM(BS59:BV59) -> 8175 | DG59: =SUM(BW59:BZ59) -> 9425 | DH59: =SUM(CA59:CD59) -> 8705.15 | DI59: =SUM(CE59:CH59) -> 8646 | DJ59: =SUM(CI59:CL59) -> 8947 | DK59: =SUM(CM59:CP59) -> 9388.1405 | DL59: =+DL58-DL60 -> 9402.104 | DM59: =+DM58-DM60 -> 9799.669 | DN59: =+DN58-DN60 -> 9857.0076 | DO59: =+DO58-DO60 -> 10018.246 | DP59: =+DP58-DP60 -> 8761.6822
B60: Gross Profit | AQ60: =+AQ58-AQ59 -> 3176 | AR60: =+AR58-AR59 -> 3638 | AS60: =+AS58-AS59 -> 3566 | AT60: =+AT58-AT59 -> 3829 | AU60: =+AU58-AU59 -> 3463 | AV60: =+AV58-AV59 -> 3891 | AW60: =+AW58-AW59 -> 3925 | AX60: =+AX58-AX59 -> 4333 | ... BP60: =+BP58-BP59 -> 6828 | BQ60: =BQ58-BQ59 -> 6954 | BR60: =BR58-BR59 -> 7099 | BS60: =BS58-BS59 -> 7125 | BT60: =BT58-BT59 -> 8629 | BU60: =BU58-BU59 -> 10520 | BV60: =BV58-BV59 -> 11335 | BW60: =BW58-BW59 -> 10850 | BX60: =BX58-BX59 -> 11480 | ... CB60: =CB58-CB59 -> 12416 | CC60: =+CC58-CC59 -> 12645 | CD60: =+CD58*0.85 -> 12852.85 | CE60: =CE58-CE59 -> 10294 | CF60: =+CF58-CF59 -> 11748 | CG60: =+CG58-CG59 -> 11626 | CH60: =+CH58-CH59 -> 12004 | CI60: =+CI58-CI59 -> 10202 | CJ60: =+CJ58-CJ59 -> 12327 | CK60: =+CK58-CK59 -> 12209 | CL60: =+CL58-CL59 -> 12649 | CM60: =+CM58-CM59 -> 11116.1 | CN60: =+CN58-CN59 -> 13010 | CO60: =+CO58*0.85 -> 13409.829 | CP60: =+CP58*0.85 -> 14125.3 | DD60: =+DD58-DD59 -> 26371 | DE60: =+DE58-DE59 -> 27406 | DF60: =+DF58-DF59 -> 37609 | DG60: =+DG58-DG59 -> 46697 | DH60: =+DH58-DH59 -> 49348.85 | DI60: =+DI58-DI59 -> 45672 | DJ60: =+DJ58-DJ59 -> 47387 | DK60: =+DK58-DK59 -> 51641.229 | DL60: =+DL58*0.85 -> 53278.589 | DM60: =+DM58*0.85 -> 55531.458 | DN60: =+DN58*0.85 -> 55856.376 | DO60: =+DO58*0.85 -> 56770.063 | DP60: =+DP58*0.85 -> 49649.532
B61: SG&A | AQ61: 1237 | AR61: 1406 | AS61: 1261 | AT61: 1448 | AU61: 1340 | AV61: =1448-96-6 -> 1346 | AW61: 1595 | AX61: 3341 | AY61: 1473 | AZ61: 1703 | BA61: 1474 | BB61: 1737 | BC61: 1355 | BD61: 1466 | BE61: 1368 | BF61: 1625 | BG61: 1360 | BH61: 1405 | BI61: 1448 | BJ61: 1641 | BK61: 1670 | BL61: 1643 | BM61: 1575 | BN61: 1797 | BO61: 1563 | BP61: 1620 | BQ61: 1621 | BR61: 1883 | BS61: 1599 | BT61: 2392 | BU61: 2723 | BV61: 3089 | BW61: 2743 | BX61: 2953 | BY61: 2961 | BZ61: 3307 | CA61: 2852 | CB61: 3089 | CC61: 3089 | CD61: =+BZ61*1.01 -> 3340.07 | CE61: 2984 | CF61: 3218 | CG61: 3330 | CH61: 3540 | CI61: 3032 | CJ61: 3315 | CK61: 3326 | CL61: 3561 | CM61: 3280 | CN61: 3239 | CO61: =+CK61*1.05 -> 3492.3 | CP61: =+CL61*1.05 -> 3739.05 | DD61: =SUM(BK61:BN61) -> 6685 | DE61: =SUM(BO61:BR61) -> 6687 | DF61: =SUM(BS61:BV61) -> 9803 | DG61: =SUM(BW61:BZ61) -> 11964 | DH61: =SUM(CA61:CD61) -> 12370.07 | DI61: =SUM(CE61:CH61) -> 13072 | DJ61: =SUM(CI61:CL61) -> 13234 | DK61: =SUM(CM61:CP61) -> 13750.35 | DL61: =+DL58*0.2 -> 12536.139 | DM61: =+DM58*0.2 -> 13066.225 | DN61: =+DN58*0.2 -> 13142.677 | DO61: =+DO58*0.2 -> 13357.662 | DP61: =+DP58*0.2 -> 11682.243
B62: R&D | AQ62: 634 | AR62: 709 | AS62: 714 | AT62: 798 | AU62: 772 | AV62: =834-41 -> 793 | AW62: 812 | AX62: 879 | AY62: 811 | AZ62: 981 | BA62: 1418 | BB62: 1075 | BC62: 946 | BD62: 1124 | BE62: 1051 | BF62: 1175 | BG62: 1112 | BH62: 1212 | BI62: 1190 | BJ62: 1322 | BK62: 1189 | BL62: 1267 | BM62: 1268 | BN62: 1369 | BO62: 1199 | BP62: 1232 | BQ62: 1227 | BR62: 1331 | BS62: 1234 | BT62: 1332 | BU62: 1513 | BV62: 1751 | BW62: 1505 | BX62: 1583 | BY62: 1632 | BZ62: 1798 | CA62: 1480 | CB62: 1607 | CC62: 1607 | CD62: =+BZ62*1.01 -> 1815.98 | CE62: 1657 | CF62: 1730 | CG62: 1720 | CH62: 1992 | CI62: 1811 | CJ62: 1917 | CK62: 2055 | CL62: 2273 | CM62: 2051 | CN62: 2115 | CO62: =+CK62*1.05 -> 2157.75 | CP62: =+CL62*1.05 -> 2386.65 | DD62: =SUM(BK62:BN62) -> 5093 | DE62: =SUM(BO62:BR62) -> 4989 | DF62: =SUM(BS62:BV62) -> 5830 | DG62: =SUM(BW62:BZ62) -> 6518 | DH62: =SUM(CA62:CD62) -> 6509.98 | DI62: =SUM(CE62:CH62) -> 7099 | DJ62: =SUM(CI62:CL62) -> 8056 | DK62: =SUM(CM62:CP62) -> 8710.4
B63: Operating Expenses | AQ63: =+AQ62+AQ61 -> 1871 | AR63: =+AR62+AR61 -> 2115 | AS63: =+AS62+AS61 -> 1975 | AT63: =+AT62+AT61 -> 2246 | AU63: =+AU62+AU61 -> 2112 | AV63: =+AV62+AV61 -> 2139 | AW63: =+AW62+AW61 -> 2407 | AX63: =+AX62+AX61 -> 4220 | ... BB63: =+BB62+BB61 -> 2812 | BC63: =+BC61+BC62 -> 2301 | BD63: =+BD61+BD62 -> 2590 | BE63: =+BE61+BE62 -> 2419 | BF63: =+BF61+BF62 -> 2800 | BG63: =+BG61+BG62 -> 2472 | BH63: =+BH61+BH62 -> 2617 | BI63: =+BI61+BI62 -> 2638 | BJ63: =+BJ61+BJ62 -> 2963 | ... BP63: =+BP61+BP62 -> 2852 | BQ63: =BQ62+BQ61 -> 2848 | BR63: =BR62+BR61 -> 3214 | BS63: =BS62+BS61 -> 2833 | BT63: =BT62+BT61 -> 3724 | BU63: =BU62+BU61 -> 4236 | BV63: =BV62+BV61 -> 4840 | BW63: =BW62+BW61 -> 4248 | BX63: =BX62+BX61 -> 4536 | ... CH63: =CH62+CH61 -> 5532 | CI63: =+CI61+CI62 -> 4843 | CJ63: =+CJ61+CJ62 -> 5232 | CK63: =+CK61+CK62 -> 5381 | CL63: =+CL61+CL62 -> 5834 | CM63: =+CM61+CM62 -> 5331 | CN63: =+CN61+CN62 -> 5354 | CO63: =+CO61+CO62 -> 5650.05 | CP63: =+CP61+CP62 -> 6125.7 | DD63: =+DD61+DD62 -> 11778 | DE63: =+DE61+DE62 -> 11676 | DF63: =+DF61+DF62 -> 15633 | DG63: =+DG61+DG62 -> 18482 | DH63: =+DH61+DH62 -> 18880.05 | DI63: =+DI61+DI62 -> 20171 | DJ63: =+DJ61+DJ62 -> 21290 | DK63: =+DK61+DK62 -> 22460.75 | ... DP63: =+DP61+DP62 -> 11682.243
B64: Operating Income | AQ64: =AQ60-AQ63 -> 1305 | AR64: =AR60-AR63 -> 1523 | AS64: =AS60-AS63 -> 1591 | AT64: =AT60-AT63 -> 1583 | AU64: =AU60-AU63 -> 1351 | AV64: =+AV60-AV63 -> 1752 | AW64: =+AW60-AW63 -> 1518 | AX64: =+AX60-AX63 -> 113 | AY64: =+AY60-AY63 -> 1814 | AZ64: =+AZ60-AZ63 -> 1875 | BA64: =+BA60-BA63 -> 1885 | BB64: =+BB60-BB63 -> 2073 | BC64: =+BC60-BC63 -> 2288 | ... BP64: =+BP60-BP63 -> 3976 | BQ64: =BQ60-BQ63 -> 4106 | BR64: =BR60-BR63 -> 3885 | BS64: =BS60-BS63 -> 4292 | BT64: =BT60-BT63 -> 4905 | BU64: =BU60-BU63 -> 6284 | BV64: =BV60-BV63 -> 6495 | BW64: =BW60-BW63 -> 6602 | BX64: =BX60-BX63 -> 6944 | ... CH64: =CH60-CH63 -> 6472 | CI64: =+CI60-CI63 -> 5359 | CJ64: =+CJ60-CJ63 -> 7095 | CK64: =+CK60-CK63 -> 6828 | CL64: =+CL60-CL63 -> 6815 | CM64: =+CM60-CM63 -> 5785.1 | CN64: =+CN60-CN63 -> 7656 | CO64: =+CO60-CO63 -> 7759.7795 | CP64: =+CP60-CP63 -> 7999.6 | DD64: =+DD60-DD63 -> 14593 | DE64: =+DE60-DE63 -> 15730 | DF64: =+DF60-DF63 -> 21976 | DG64: =+DG60-DG63 -> 28215 | DH64: =+DH60-DH63 -> 30468.8 | DI64: =+DI60-DI63 -> 25501 | DJ64: =+DJ60-DJ63 -> 26097 | DK64: =+DK60-DK63 -> 29180.479 | ... DP64: =+DP60-DP63 -> 37967.289
B65: Interest Income | AQ65: =-66-15+15 -> -66 | AR65: =-75+4 -> -71 | AS65: =-69-11-5 -> -85 | AT65: =-68-13 -> -81 | AU65: =-65+3 -> -62 | AV65: =-69-5-8 -> -82 | AW65: =-128-221 -> -349 | AX65: =-129+3 -> -126 | AY65: =-126-1 -> -127 | AZ65: =-164+4 -> -160 | BA65: =-197-28 -> -225 | BB65: =-199+12 -> -187 | BC65: -200 | BD65: =-225-51 -> -276 | BE65: =-250+3 -> -247 | BF65: =-251+5 -> -246 | BG65: =-247+25 -> -222 | BH65: -253 | BI65: =-252+52 -> -200 | BJ65: =-252+50 -> -202 | BK65: =5-251 -> -246 | BL65: =-15-272 -> -287 | BM65: =-302-2+1 -> -303 | BN65: =-319-6+11 -> -314 | BO65: =34-325 -> -291 | BP65: =-302+26 -> -276 | BQ65: =-288-19+3 -> -304 | BR65: =-282-11+22 -> -271 | BS65: =-284-5 -> -289 | BT65: =-484+7-33 -> -510 | BU65: 620 | BV65: 618 | BW65: -622 | BX65: -606 | BY65: -585 | BZ65: -571 | CA65: =-539+28 -> -511 | CB65: =-497+210 -> -287 | CC65: =120-497 -> -377 | CD65: =+CC65 -> -377 | CE65: 69 | CF65: =-119-454 -> -573 | CG65: =146-398 -> -252 | CH65: =-363+142 -> -221 | CI65: =-429+76 -> -353 | CJ65: =153-506-1 -> -354 | CK65: =199-591 -> -392 | CL65: =201-610 -> -409 | CM65: =-627+82 -> -545 | CN65: =-678+172 -> -506 | CO65: =+CN65 -> -506 | CP65: =+CO65 -> -506 | DD65: =SUM(BK65:BN65) -> -1150 | DE65: =SUM(BO65:BR65) -> -1142 | DF65: =SUM(BS65:BV65) -> 439 | DG65: =SUM(BW65:BZ65) -> -2384 | DH65: =SUM(CA65:CD65) -> -1552 | DI65: =SUM(CE65:CH65) -> -977 | DJ65: =SUM(CI65:CL65) -> -1508 | DK65: =SUM(CM65:CP65) -> -2063 | DL65: =+DK65+300 -> -1763 | DM65: =+DL65+300 -> -1463 | DN65: =+DM65+300 -> -1163 | DO65: =+DN65+300 -> -863 | DP65: =+DO65+300 -> -563
B66: Pretax Income | AQ66: =+AQ64+AQ65 -> 1239 | AR66: =+AR64+AR65 -> 1452 | AS66: =+AS64+AS65 -> 1506 | AT66: =+AT64+AT65 -> 1502 | AU66: =+AU64+AU65 -> 1289 | AV66: =+AV65+AV64 -> 1670 | AW66: =+AW65+AW64 -> 1169 | AX66: =+AX65+AX64 -> -13 | AY66: =+AY65+AY64 -> 1687 | AZ66: =+AZ65+AZ64 -> 1715 | BA66: =+BA65+BA64 -> 1660 | BB66: =+BB65+BB64 -> 1886 | BC66: =+BC64+BC65 -> 2088 | BD66: =+BD64+BD65 -> 2161 | BE66: =+BE64+BE65 -> 2485 | BF66: =+BF64+BF65 -> 2451 | BG66: =+BG64+BG65 -> 2531 | BH66: =+BH64+BH65 -> 2843 | BI66: =+BI64+BI65 -> 2815 | BJ66: =+BJ64+BJ65 -> 2949 | ... BP66: =+BP64+BP65 -> 3700 | BQ66: =BQ64+BQ65 -> 3802 | BR66: =BR64+BR65 -> 3614 | BS66: =BS64+BS65 -> 4003 | BT66: =BT64+BT65 -> 4395 | BU66: =BU64+BU65 -> 6904 | BV66: =BV64+BV65 -> 7113 | BW66: =BW64+BW65 -> 5980 | BX66: =BX64+BX65 -> 6338 | ... CH66: =CH64+CH65 -> 6251 | CI66: =+CI64+CI65 -> 5006 | CJ66: =+CJ64+CJ65 -> 6741 | CK66: =+CK64+CK65 -> 6436 | CL66: =+CL64+CL65 -> 6406 | CM66: =+CM64+CM65 -> 5240.1 | CN66: =+CN64+CN65 -> 7150 | CO66: =+CO64+CO65 -> 7253.7795 | CP66: =+CP64+CP65 -> 7493.6 | DD66: =+DD64+DD65 -> 13443 | DE66: =+DE64+DE65 -> 14588 | DF66: =+DF64+DF65 -> 22415 | DG66: =+DG64+DG65 -> 25831 | DH66: =+DH64+DH65 -> 28916.8 | DI66: =+DI64+DI65 -> 24524 | DJ66: =+DJ64+DJ65 -> 24589 | DK66: =+DK64+DK65 -> 27117.479 | ... DP66: =+DP64+DP65 -> 37404.289
B67: Taxes | AQ67: 271 | AR67: 300 | AS67: 322 | AT67: 311 | AU67: 306 | AV67: 335 | AW67: 181 | AX67: 0 | AY67: 374 | AZ67: 312 | BA67: 408 | BB67: 407 | BC67: 422 | BD67: 486 | BE67: 495 | BF67: 497 | BG67: 458 | BH67: 548 | BI67: 533 | BJ67: 556 | BK67: 249 | BL67: 311 | BM67: 326 | BN67: 289 | BO67: 274 | BP67: 324 | BQ67: 334 | BR67: 320 | BS67: 390 | BT67: 501 | BU67: 668 | BV67: 686 | BW67: 738 | BX67: =799+3 -> 802 | BY67: =862+1 -> 863 | BZ67: =6764-5919 -> 845 | CA67: 778 | CB67: 965 | CC67: 965 | CD67: =+CD66*0.15 -> 1097.97 | CE67: =6422-5641 -> 781 | CF67: =583+3 -> 586 | CG67: 980 | CH67: =388+2 -> 390 | CI67: 715 | CJ67: 1091 | CK67: 1027 | CL67: 970 | CM67: 726 | CN67: 1023 | CO67: =+CO66*0.1 -> 725.37795 | CP67: =+CP66*0.1 -> 749.36 | DD67: =SUM(BK67:BN67) -> 1175 | DE67: =SUM(BO67:BR67) -> 1252 | DF67: =SUM(BS67:BV67) -> 2245 | DG67: =SUM(BW67:BZ67) -> 3248 | DH67: =SUM(CA67:CD67) -> 3805.97 | DI67: =SUM(CE67:CH67) -> 2737 | DJ67: =SUM(CI67:CL67) -> 3803 | DK67: =SUM(CM67:CP67) -> 3223.7379 | DL67: =+DL66*0.15 -> 5846.9176 | DM67: =+DM66*0.15 -> 6150.3348 | DN67: =+DN66*0.15 -> 6232.6049 | DO67: =+DO66*0.15 -> 6382.4102 | DP67: =+DP66*0.15 -> 5610.6434
B68: Net Income | AQ68: =+AQ66-AQ67 -> 968 | AR68: =+AR66-AR67 -> 1152 | AS68: =+AS66-AS67 -> 1184 | AT68: =+AT66-AT67 -> 1191 | AU68: =+AU66-AU67 -> 983 | AV68: =+AV66-AV67 -> 1335 | AW68: =+AW66-AW67 -> 988 | AX68: =+AX66-AX67 -> -13 | ... BP68: =+BP66-BP67 -> 3376 | BQ68: =BQ66-BQ67 -> 3468 | BR68: =BR66-BR67 -> 3294 | BS68: =BS66-BS67 -> 3613 | BT68: =BT66-BT67 -> 3894 | BU68: =BU66-BU67 -> 6236 | BV68: =BV66-BV67 -> 6427 | BW68: =BW66-BW67 -> 5242 | BX68: =BX66-BX67 -> 5536 | ... CP68: =CP66-CP67 -> 6744.24 | DD68: =+DD66-DD67 -> 12268 | DE68: =+DE66-DE67 -> 13336 | DF68: =+DF66-DF67 -> 20170 | DG68: =+DG66-DG67 -> 22583 | DH68: =+DH66-DH67 -> 25110.83 | DI68: =+DI66-DI67 -> 21787 | DJ68: =+DJ66-DJ67 -> 20786 | DK68: =+DK66-DK67 -> 23893.742 | ... DP68: =+DP66-DP67 -> 31793.646 | DQ68: =DP68*(1+$DX$76) -> 31475.709 | DR68: =DQ68*(1+$DX$76) -> 31160.952 | DS68: =DR68*(1+$DX$76) -> 30849.343 | DT68: =DS68*(1+$DX$76) -> 30540.849 | DU68: =DT68*(1+$DX$76) -> 30235.441 | DV68: =DU68*(1+$DX$76) -> 29933.087 | DW68: =DV68*(1+$DX$76) -> 29633.756 | DX68: =DW68*(1+$DX$76) -> 29337.418 | ... IM68: =IL68*(1+$DX$76) -> 8871.7654
B69: EPS | AQ69: =AQ68/AQ70 -> 0.60311526 | AR69: =AR68/AR70 -> 0.71597265 | AS69: =AS68/AS70 -> 0.74465409 | AT69: =AT68/AT70 -> 0.74067164 | AU69: =AU68/AU70 -> 0.61093847 | AV69: =AV68/AV70 -> 0.83022388 | AW69: =AW68/AW70 -> 0.6136646 | AX69: =AX68/AX70 -> -0.008140263 | ... CP69: =CP68/CP70 -> 3.8081536 | DD69: =+DD68/DD70 -> 7.9353169 | DE69: =+DE68/DE70 -> 8.9880371 | DF69: =+DF68/DF70 -> 12.076037 | DG69: =+DG68/DG70 -> 12.712074 | DH69: =+DH68/DH70 -> 14.135001 | DI69: =+DI68/DI70 -> 12.291678 | DJ69: =+DJ68/DJ70 -> 11.730248 | DK69: =+DK68/DK70 -> 13.489762 | ... DP69: =+DP68/DP70 -> 17.949835
B70: Shares | AQ70: 1605 | AR70: 1609 | AS70: 1590 | AT70: 1608 | AU70: 1609 | AV70: 1608 | AW70: 1610 | AX70: 1597 | AY70: 1608 | AZ70: 1633 | BA70: 1664 | BB70: 1640 | BC70: 1625 | BD70: 1632 | BE70: 1640 | BF70: 1602 | BG70: 1603 | BH70: 1600 | BI70: 1603 | BJ70: 1602 | BK70: 1596 | BL70: 1572 | BM70: 1515 | BN70: 1501 | BO70: 1483 | BP70: 1484 | BQ70: 1483 | BR70: 1485 | BS70: 1484 | BT70: 1647 | BU70: 1774 | BV70: 1776 | BW70: 1775 | BX70: 1776 | BY70: 1777 | BZ70: 1778 | CA70: 1778 | CB70: 1776 | CC70: 1776 | CD70: =+CC70 -> 1776 | CE70: 1776 | CF70: 1771 | CG70: 1771 | CH70: 1772 | CI70: 1772 | CJ70: 1771 | CK70: 1772 | CL70: 1773 | CM70: 1772 | CN70: 1771 | CO70: =+CN70 -> 1771 | CP70: =+CO70 -> 1771 | DD70: =AVERAGE(BK70:BN70) -> 1546 | DE70: =AVERAGE(BO70:BR70) -> 1483.75 | DF70: =AVERAGE(BS70:BV70) -> 1670.25 | DG70: =AVERAGE(BW70:BZ70) -> 1776.5 | DH70: =AVERAGE(CA70:CD70) -> 1776.5 | DI70: =AVERAGE(CE70:CH70) -> 1772.5 | DJ70: =AVERAGE(CI70:CL70) -> 1772 | DK70: =AVERAGE(CM70:CP70) -> 1771.25 | DL70: =DK70 -> 1771.25 | DM70: =DL70 -> 1771.25 | DN70: =DM70 -> 1771.25 | DO70: =DN70 -> 1771.25 | DP70: =DO70 -> 1771.25
B72: Revenue y/y | BG72: =+BG58/BC58-1 -> 0.097348103 | BH72: =+BH58/BD58-1 -> 0.07960199 | BI72: =+BI58/BE58-1 -> 0.095364861 | BJ72: =+BJ58/BF58-1 -> 0.14077241 | BK72: =+BK58/BG58-1 -> 0.21352095 | BL72: =+BL58/BH58-1 -> 0.18922811 | BM72: =+BM58/BI58-1 -> 0.17741244 | BN72: =+BN58/BJ58-1 -> 0.073136064 | ... CP72: =+CP58/CL58-1 -> 0.10038406 | DE72: =+DE58/DD58-1 -> 0.016283262 | DF72: =+DF58/DE58-1 -> 0.37630013 | DG72: =+DG58/DF58-1 -> 0.22579941 | DH72: =+DH58/DG58-1 -> 0.034425003 | DI72: =+DI58/DH58-1 -> -0.064353877 | DJ72: =+DJ58/DI58-1 -> 0.037114769 | DK72: =+DK58/DJ58-1 -> 0.083348777 | DL72: =+DL58/DK58-1 -> 0.027057849 | ... DU72: =+DU58/DT58-1 -> 0.025542056
B73: Revenue c/c | BK73: 0.176 | BL73: 0.171 | BM73: 0.185 | BN73: 0.083 | BO73: 0.004 | BP73: 0.015 | BZ73: 0.074 | CA73: 0.054 | CB73: 0.061 | CC73: 0.054 | CD73: 0.038 | CE73: -0.083 | CG73: -0.058 | CH73: -0.054 | CI73: 0.016 | CJ73: 0.056 | CK73: 0.049 | CL73: 0.06 | CM73: 0.098 | CN73: 0.065
B74: Humira y/y | BK74: =+BK5/BG5-1 -> 0.14351627 | BL74: =+BL5/BH5-1 -> 0.099448685 | BM74: =+BM5/BI5-1 -> 0.089980855 | BN74: =+BN5/BJ5-1 -> 0.0053147997 | BO74: =+BO5/BK5-1 -> -0.055850499 | BP74: =+BP5/BL5-1 -> -0.06075217 | BQ74: =+BQ5/BM5-1 -> -0.036690086 | BR74: =+BR5/BN5-1 -> -0.00020333469 | ... CP74: =+CP5/CL5-1 -> -0.25921522 | DE74: =+DE5/DD5-1 -> -0.038473114 | DF74: =+DF5/DE5-1 -> 0.034587094 | DG74: =+DG5/DF5-1 -> 0.043465107 | DH74: =+DH5/DG5-1 -> 0.02623949 | DI74: =+DI5/DH5-1 -> -0.32174978 | DJ74: =+DJ5/DI5-1 -> -0.37565954 | DK74: =+DK5/DJ5-1 -> -0.4951629 | DL74: =+DL5/DK5-1 -> -0.2 | ... DP74: =+DP5/DO5-1 -> -0.5
B75: Imbruvica y/y | BK75: =+BK7/BG7-1 -> 0.38294011 | BL75: =+BL7/BH7-1 -> 0.35782748 | BM75: =+BM7/BI7-1 -> 0.4127907 | BN75: =+BN7/BJ7-1 -> 0.42090395 | BO75: =+BO7/BK7-1 -> 0.34120735 | BP75: =+BP7/BL7-1 -> 0.29294118 | BQ75: =+BQ7/BM7-1 -> 0.29320988 | BR75: =+BR7/BN7-1 -> 0.28827038 | ... CP75: =+CP7/CL7-1 -> -0.20872642 | DE75: =+DE7/DD7-1 -> 0.30194986 | DF75: =+DF7/DE7-1 -> 0.13692769 | DG75: =+DG7/DF7-1 -> 0.017689123 | DH75: =+DH7/DG7-1 -> -0.15532544 | DI75: =+DI7/DH7-1 -> -0.21278459 | DJ75: =+DJ7/DI7-1 -> -0.069243604 | DK75: =+DK7/DJ7-1 -> -0.10137437 | DL75: =+DL7/DK7-1 -> -0.1 | ... DP75: =+DP7/DO7-1 -> -0.1 | DW75: Discount | DX75: 0.06
B76: Skyrizi y/y | BF76: - | BG76: - | BH76: - | BI76: - | BJ76: - | BK76: - | BL76: - | BM76: - | BN76: - | BO76: - | BP76: - | BQ76: - | BR76: - | BS76: - | BT76: =+BT8/BP8-1 -> 5.875 | BU76: =+BU8/BQ8-1 -> 3.7802198 | BV76: =+BV8/BR8-1 -> 1.4305556 | BW76: =+BW8/BS8-1 -> 0.91333333 | BX76: =+BX8/BT8-1 -> 1.0424242 | BY76: =+BY8/BU8-1 -> 0.82988506 | BZ76: =+BZ8/BV8-1 -> 0.7047619 | CA76: =+CA8/BW8-1 -> 0.63763066 | ... CP76: =+CP8/CL8-1 -> 0.3250397 | DE76: - | DF76: =+DF8/DE8-1 -> 3.4788732 | DG76: =+DG8/DF8-1 -> 0.84842767 | DH76: =+DH8/DG8-1 -> 0.75740048 | DI76: =+DI8/DH8-1 -> 0.50300097 | DJ76: =+DJ8/DI8-1 -> 0.50946799 | DK76: =+DK8/DJ8-1 -> 0.49871992 | DL76: =+DL8/DK8-1 -> 0.03 | DM76: =+DM8/DL8-1 -> 0.03 | ... DP76: =+DP8/DO8-1 -> 0.03 | DW76: Terminal | DX76: -0.01
B77: Immunology y/y | BO77: =+BO3/BK3-1 -> -0.055850499 | BP77: =+BP3/BL3-1 -> -0.051494696 | BQ77: =+BQ3/BM3-1 -> -0.016198283 | BR77: =+BR3/BN3-1 -> 0.050427003 | BS77: =+BS3/BO3-1 -> 0.14462438 | BT77: =+BT3/BP3-1 -> 0.080927206 | BU77: =+BU3/BQ3-1 -> 0.14858163 | BV77: =+BV3/BR3-1 -> 0.1533101 | ... CP77: =+CP3/CL3-1 -> 0.18261585 | DE77: =+Model!DE3/Model!DD3-1 -> -0.018308587 | DF77: =+Model!DF3/Model!DE3-1 -> 0.1319299 | DG77: =+Model!DG3/Model!DF3-1 -> 0.14133526 | DH77: =+Model!DH3/Model!DG3-1 -> 0.14396456 | DI77: =+Model!DI3/Model!DH3-1 -> -0.096390541 | DJ77: =+Model!DJ3/Model!DI3-1 -> 0.020890725 | DK77: =+Model!DK3/Model!DJ3-1 -> 0.13956975 | DL77: =+Model!DL3/Model!DK3-1 -> 0.042085773 | ... DP77: =+Model!DP3/Model!DO3-1 -> 0.018396367 | DW77: ROIC | DX77: 0
B78: Botox Cosmetic | BF78: - | BG78: - | BH78: - | BI78: - | BJ78: - | BK78: - | BL78: - | BM78: - | BN78: - | BO78: - | BP78: - | BQ78: - | BR78: - | BS78: - | BT78: - | BU78: - | BV78: - | BW78: - | BX78: =BX9/BT9-1 -> 1.5840708 | BY78: =BY9/BU9-1 -> 0.38676845 | BZ78: =BZ9/BV9-1 -> 0.26977688 | CA78: =CA9/BW9-1 -> 0.34381551 | CB78: =CB9/BX9-1 -> 0.19006849 | CC78: =CC9/BY9-1 -> 0.16880734 | CD78: =CD9/BZ9-1 -> 0.025559105 | CE78: =CE9/CA9-1 -> 0.028081123 | ... CP78: =CP9/CL9-1 -> 0.043668122 | DG78: =+DG9/DF9-1 -> 1.0071942 | DH78: =+DH9/DG9-1 -> 0.17159498 | DI78: =+DI9/DH9-1 -> 0.025621415 | DJ78: =+DJ9/DI9-1 -> 0.014168531 | DK78: =+DK9/DJ9-1 -> -0.038283088 | DL78: =+DL9/DK9-1 -> 0.05 | DM78: =+DM9/DL9-1 -> 0.05 | DN78: =+DN9/DM9-1 -> 0.05 | ... DP78: =+DP9/DO9-1 -> 0.05 | DW78: NPV | DX78: =NPV(DX75,DI68:IM68)+Main!K5-Main!K6 -> 398666.76
B79: Botox Therapeutic | BF79: - | BG79: - | BH79: - | BI79: - | BJ79: - | BK79: - | BL79: - | BM79: - | BN79: - | BO79: - | BP79: - | BQ79: - | BR79: - | BS79: - | BT79: - | BU79: - | BV79: - | BW79: - | BX79: =BX10/BT10-1 -> 1.030303 | BY79: =BY10/BU10-1 -> 0.2332696 | BZ79: =BZ10/BV10-1 -> 0.18342152 | CA79: =CA10/BW10-1 -> 0.15413534 | CB79: =CB10/BX10-1 -> 0.12437811 | CC79: =CC10/BY10-1 -> 0.08372093 | CD79: =CD10/BZ10-1 -> 0.084947839 | CE79: =CE10/CA10-1 -> 0.17100977 | ... CP79: =CP10/CL10-1 -> 0.13402062 | DG79: =+DG10/DF10-1 -> 0.76712329 | DH79: =+DH10/DG10-1 -> 0.10934313 | DI79: =+DI10/DH10-1 -> 0.10003678 | DJ79: =+DJ10/DI10-1 -> 0.097626212 | DK79: =+DK10/DJ10-1 -> 0.13213524 | DL79: =+DL10/DK10-1 -> 0.05 | DM79: =+DM10/DL10-1 -> 0.05 | DN79: =+DN10/DM10-1 -> 0.05 | ... DP79: =+DP10/DO10-1 -> 0.05 | DW79: Share | DX79: =DX78/Main!K3 -> 225.10828
B80: Rinvoq y/y | BF80: - | BG80: - | BH80: - | BI80: - | BJ80: - | BK80: - | BL80: - | BM80: - | BN80: - | BO80: - | BP80: - | BQ80: - | BR80: - | BS80: - | BT80: - | BU80: =BU13/BQ13-1 -> 14.357143 | BV80: =BV13/BR13-1 -> 7.5151515 | BW80: =BW13/BS13-1 -> 2.5232558 | BX80: =BX13/BT13-1 -> 1.5369128 | BY80: =BY13/BU13-1 -> 1.1069767 | BZ80: =BZ13/BV13-1 -> 0.83985765 | CA80: =CA13/BW13-1 -> 0.53465347 | CB80: =CB13/BX13-1 -> 0.56613757 | ... CP80: =CP13/CL13-1 -> 0.29443839 | DG80: =+DG13/DF13-1 -> 1.2585499 | DH80: =+DH13/DG13-1 -> 0.52755906 | DI80: =+DI13/DH13-1 -> 0.57375099 | DJ80: =+DJ13/DI13-1 -> 0.50440917 | DK80: =+DK13/DJ13-1 -> 0.39072182 | DL80: =+DL13/DK13-1 -> 0.2 | DM80: =+DM13/DL13-1 -> 0.2 | DN80: =+DN13/DM13-1 -> 0.03 | ... DP80: =+DP13/DO13-1 -> 0.03
B81: Vraylar y/y | BX81: =BX14/BT14-1 -> 1.25 | BY81: =BY14/BU14-1 -> 0.2877095 | BZ81: =BZ14/BV14-1 -> 0.21945137 | CA81: =CA14/BW14-1 -> 0.23410405 | CB81: =CB14/BX14-1 -> 0.13888889 | CC81: =CC14/BY14-1 -> 0.20173536 | CD81: =CD14/BZ14-1 -> 0.15541922 | CE81: =CE14/CA14-1 -> 0.31381733 | ... CP81: =CP14/CL14-1 -> 0.10606061 | DG81: =+DG14/DF14-1 -> 0.8170347 | DH81: =+DH14/DG14-1 -> 0.17939815 | DI81: =+DI14/DH14-1 -> 0.35377821 | DJ81: =+DJ14/DI14-1 -> 0.18412468 | DK81: =+DK14/DJ14-1 -> 0.10835629 | DL81: =+DL14/DK14-1 -> 0.03 | DM81: =+DM14/DL14-1 -> 0.03 | DN81: =+DN14/DM14-1 -> 0.03 | ... DP81: =+DP14/DO14-1 -> -0.9
B84: Gross Margin | BI84: =+BI60/BI58 -> 0.80814868 | BJ84: =+BJ60/BJ58 -> 0.79002455 | BK84: =+BK60/BK58 -> 0.80186539 | BL84: =+BL60/BL58 -> 0.80540082 | BM84: =+BM60/BM58 -> 0.81677999 | BN84: =+BN60/BN58 -> 0.79843468 | BO84: =+BO60/BO58 -> 0.83354624 | BP84: =+BP60/BP58 -> 0.82713507 | ... CP84: =+CP60/CP58 -> 0.85 | DD84: =+DD60/DD58 -> 0.80563957 | DE84: =+DE60/DE58 -> 0.82384417 | DF84: =+DF60/DF58 -> 0.82144417 | DG84: =+DG60/DG58 -> 0.83206229 | DH84: =+DH60/DH58 -> 0.85005081 | DI84: =+DI60/DI58 -> 0.84082625 | DJ84: =+DJ60/DJ58 -> 0.84117939 | DK84: =+DK60/DK58 -> 0.84617012 | ... DP84: =+DP60/DP58 -> 0.85
B85: Tax Rate | BI85: =+BI67/BI66 -> 0.18934281 | BJ85: =+BJ67/BJ66 -> 0.18853849 | BK85: =+BK67/BK66 -> 0.076450722 | BL85: =+BL67/BL66 -> 0.090040533 | BM85: =+BM67/BM66 -> 0.091036023 | BN85: =+BN67/BN66 -> 0.091716915 | BO85: =+BO67/BO66 -> 0.078917051 | BP85: =+BP67/BP66 -> 0.087567568 | ... CP85: =+CP67/CP66 -> 0.1 | DD85: =+DD67/DD66 -> 0.087406085 | DE85: =+DE67/DE66 -> 0.085823965 | DF85: =+DF67/DF66 -> 0.10015615 | DG85: =+DG67/DG66 -> 0.12574039 | DH85: =+DH67/DH66 -> 0.13161795 | DI85: =+DI67/DI66 -> 0.11160496 | DJ85: =+DJ67/DJ66 -> 0.15466265 | DK85: =+DK67/DK66 -> 0.11888044 | ... DP85: =+DP67/DP66 -> 0.15
B87: Net Cash | CA87: =CA88-CA97 -> -65642 | CB87: =CB88-CB97 -> -62727 | CC87: =CC88-CC97 -> -57492 | CD87: =CD88-CD97 -> 0 | CE87: =CE88-CE97 -> -55114 | CF87: =CF88-CF97 -> -51961 | CG87: =CG88-CG97 -> -47181 | CH87: =CH88-CH97 -> -46265 | ... CN87: =CN88-CN97 -> -63704
B88: Cash | CA88: =6098+1474+260 -> 7832 | CB88: =8521+1440+244 -> 10205 | CC88: =11832+47+235 -> 12114 | CE88: =6711+11+257 -> 6979 | CF88: =8759+7+288 -> 9054 | CG88: =13287+3+275 -> 13565 | CH88: =12814+2+304 -> 13120 | CI88: =18069+305 -> 18374 | CJ88: =13130+27+272 -> 13429 | CK88: =7257+28+267 -> 7552 | CL88: =5524+31+279 -> 5834 | CM88: =5175+1+287 -> 5463 | CN88: =6467+310 -> 6777
B89: AR | CA89: 10733 | CB89: 11237 | CC89: 10743 | CE89: 11473 | CF89: 11491 | CG89: 11412 | CH89: 11155 | CI89: 11949 | CJ89: 11724 | CK89: 11472 | CL89: 10919 | CM89: 12477 | CN89: 12637
B90: Inventories | CA90: 3483 | CB90: 3396 | CC90: 3172 | CE90: 3833 | CF90: 4055 | CG90: 3981 | CH90: 4099 | CI90: 4245 | CJ90: 4218 | CK90: 4450 | CL90: 4181 | CM90: 4526 | CN90: 4960
B91: Prepaids | CA91: 4721 | CB91: 4506 | CC91: 4570 | CE91: 4460 | CF91: 4540 | CG91: 4541 | CH91: 4932 | CI91: 4608 | CJ91: 4717 | CK91: 4578 | CL91: 4927 | CM91: 5496 | CN91: 5197
B92: PP&E | CA92: 5075 | CB92: 4958 | CC92: 4893 | CE92: 4931 | CF92: 4943 | CG92: 4934 | CH92: 4989 | CI92: 4980 | CJ92: 5023 | CK92: 5141 | CL92: 5134 | CM92: 5237 | CN92: 5283
B93: Goodwill | CA93: =73986+32298 -> 106284 | CB93: =71823+32028 -> 103851 | CC93: =68725+31726 -> 100451 | CE93: =64848+32220 -> 97068 | CF93: =62862+32224 -> 95086 | CG93: =58603+32091 -> 90694 | CH93: =55610+32293 -> 87903 | CI93: =62225+33426 -> 95651 | CJ93: =60243+33386 -> 93629 | CK93: =66646+35295 -> 101941 | CL93: =60068+34956 -> 95024 | CM93: =58489+35285 -> 93774 | CN93: =57031+35638 -> 92669
B94: Other | CA94: 5083 | CB94: 5033 | CC94: 5382 | CE94: 5800 | CF94: 6198 | CG94: 7094 | CH94: 8513 | CI94: 9067 | CJ94: 9197 | CK94: 8288 | CL94: 9142 | CM94: 9192 | CN94: 9659
B95: Assets | CA95: =SUM(CA88:CA94) -> 143211 | CB95: =SUM(CB88:CB94) -> 143186 | CC95: =SUM(CC88:CC94) -> 141325 | CE95: =SUM(CE88:CE94) -> 134544 | CF95: =SUM(CF88:CF94) -> 135367 | CG95: =SUM(CG88:CG94) -> 136221 | CH95: =SUM(CH88:CH94) -> 134711 | CI95: =SUM(CI88:CI94) -> 148874 | CJ95: =SUM(CJ88:CJ94) -> 141937 | CK95: =SUM(CK88:CK94) -> 143422 | CL95: =SUM(CL88:CL94) -> 135161 | ... CN95: =SUM(CN88:CN94) -> 137182
B97: Debt | CA97: =12+9940+63522 -> 73474 | CB97: =17+61002+11913 -> 72932 | CC97: =10+9197+60399 -> 69606 | CE97: =1+59292+2800 -> 62093 | CF97: =5203+55812 -> 61015 | CG97: =2+55631+5113 -> 60746 | CH97: =7191+52194 -> 59385 | CI97: =3+63805+10193 -> 74001 | CJ97: =12586+58048 -> 70634 | CK97: =12570+58509 -> 71079 | CL97: =6804+60340 -> 67144 | CM97: =1593+64527+3769 -> 69889 | CN97: =5556+62959+1966 -> 70481
B98: AP | CA98: 22569 | CB98: 22543 | CC98: 23505 | CE98: 24789 | CF98: 27036 | CG98: 29658 | CH98: 30650 | CI98: 31326 | CJ98: 29329 | CK98: 30492 | CL98: 31945 | CM98: 31041 | CN98: 32245
B99: DT | CA99: 2831 | CB99: 2255 | CC99: 1972 | CE99: 2110 | CF99: 2124 | CG99: 2044 | CH99: 1952 | CI99: 2722 | CJ99: 2726 | CK99: 2749 | CL99: 2579 | CM99: 2582 | CN99: 2554
B100: OLTL | CA100: 28023 | CB100: 30768 | CC100: 30215 | CE100: 32249 | CF100: 32294 | CG100: 31644 | CH100: 32327 | CI100: 32778 | CJ100: 32427 | CK100: 33031 | CL100: 30129 | CM100: 31191 | CN100: 32040
B101: S/E | CA101: 16314 | CB101: 14688 | CC101: 16027 | CE101: 13303 | CF101: 12898 | CG101: 12129 | CH101: 10397 | CI101: 8047 | CJ101: 6821 | CK101: 6071 | CL101: =3364 -> 3364 | CM101: 1462 | CN101: -138
B102: L+S/E | CA102: =SUM(CA97:CA101) -> 143211 | CB102: =SUM(CB97:CB101) -> 143186 | CC102: =SUM(CC97:CC101) -> 141325 | CE102: =SUM(CE97:CE101) -> 134544 | CF102: =SUM(CF97:CF101) -> 135367 | CG102: =SUM(CG97:CG101) -> 136221 | CH102: =SUM(CH97:CH101) -> 134711 | CI102: =SUM(CI97:CI101) -> 148874 | CJ102: =SUM(CJ97:CJ101) -> 141937 | CK102: =SUM(CK97:CK101) -> 143422 | CL102: =SUM(CL97:CL101) -> 135161 | ... CN102: =SUM(CN97:CN101) -> 137182
B104: Model NI | CA104: =+CA68 -> 5814 | CE104: =+CE68 -> 4941 | CF104: =+CF68 -> 5641 | CG104: =+CG68 -> 5344 | CH104: =+CH68 -> 5861 | CI104: =+CI68 -> 4291 | CJ104: =+CJ68 -> 5650 | CK104: =+CK68 -> 5409 | CL104: =+CL68 -> 5436 | ... CN104: =+CN68 -> 6127
B105: Reported NI | CA105: 4493 | CE105: 241 | CF105: =2268-CE105 -> 2027 | CG105: =4049-CF105-CE105 -> 1781 | CH105: =4873-CG105-CF105-CE105 -> 824 | CI105: 1372 | CJ105: =2745-CI105 -> 1373 | CK105: =4309-CJ105-CI105 -> 1564 | CL105: =4286-CK105-CJ105-CI105 -> -23 | CM105: 1289
B106: Depreciation | CA106: 198 | CE106: 179 | CF106: =369-CE106 -> 190 | CG106: =565-CF106-CE106 -> 196 | CH106: =752-CG106-CF106-CE106 -> 187 | CI106: 183 | CJ106: =367-CI106 -> 184 | CK106: =558-CJ106-CI106 -> 191 | CL106: =764-CK106-CJ106-CI106 -> 206 | CM106: 181
B107: Amortization | CA107: 1855 | CE107: 1948 | CF107: =4018-CE107 -> 2070 | CG107: =6057-CF107-CE107 -> 2039 | CH107: =7946-CG107-CF107-CE107 -> 1889 | CI107: 1891 | CJ107: =3838-CI107 -> 1947 | CK107: =5726-CJ107-CI107 -> 1888 | CL107: =7622-CK107-CJ107-CI107 -> 1896 | CM107: 1858
...

Sheet Skyrizi
A1: Main
B2: Brand | C2: Skyrizi, fka ABBV-006
B3: Generic | C3: risankizumab
B4: MOA | C4: IL-23
B5: Indication | C5: Crohn's, Psoriasis, Psoriatic Arthritis, UC (FDA/EC approved)
B6: Economics | C6: Boehringer Ingelheim
B7: Approval | C7: BLA 761105 approved 4/23/2019
B8: Clinical Trials
C9: Phase III "INSPIRE" UC induction
C12: Phase III "COMMAND" UC maintenance
C15: Phase III "SEQUENCE" vs Stelara Crohn's

Sheet Imbruvica
A1: Main
B2: Brand | C2: Imbruvica
B3: Generic | C3: ibrutinib
B4: Indication | C4: GvHD, MCL, CLL, MZL, WM
B5: MOA | C5: BTK
B6: IP | C6: 6/28/27 expiry
B7: Approval | C7: NDA 205552 approved 11/13/13
B8: Economics | C8: J&J international profit share

Sheet Emrelis
A1: Main
B2: Brand | C2: Emrelis
B3: Generic | C3: telisotuzumab vedotin
B4: Indication | C4: EGFR wild type NSCLC with c-Met overexpression
B5: Regulatory | C5: AA for 2L NSCLC with high c-Met
B6: MOA | C6: c-Met ADC
C7: c-Met is overexpressed in 25% of EGFRwt nsNSCLC according to the company
B8: Clinical Trials
C9: Phase III "TeliMET NSCLC-01"
C14: Phase II "LUMINOSITY"

Sheet ABBV-400
A1: Main
B2: Brand | C2: ABBV-400
B3: Generic | C3: telisotuzumab adizutecan
B4: Regulatory

Sheet Humira
A1: Main
B2: Brand Name | C2: Humira, fka D2E7
B3: Generic Name | C3: adalimumab
B4: Indications | C4: Rheumatoid Arthritis, Psoriasis, Crohn's, Ulcerative Colitis, Hidradenitis Suppurativa, Ankylosing Spondylitis, Non-Infection Uveitis, JIA
B5: MOA | C5: fully human anti-TNF mab
B6: IP | C6: Discovered via phage display
B7: Approval | C7: BLA 125057 approval 12/31/2002
B8: Economics | C8: Abbott acquired Knoll (BASF Pharma). Cambridge Antibody Technology had a royalty and was acquired by AstraZeneca.
B9: Clinical Trials

Sheet Rinvoq
A1: Main
B2: Brand | C2: Rinvoq, fka ABT-494
B3: Generic | C3: upadacitinib
B4: MOA | C4: JAK1 selective
B5: IP | C5: 8962629 expires 2031
B6: Indication | C6: Giant Cell Arteritis - 9th US indication
C7: GCA EMA filed
C8: Rheumatoid Arthritis approved (US, EU)
C9: Ulcerative Colitis approved (US, EU)
C10: PsA approved (US, EU)
B11: Clinical Trials
C12: Phase III "Measure Up 1" atopic dermatitis
C13: EASI H&N <1 was 27% for placebo, 68% for 15mg, 76% for 30mg
C15: Phase III "Measure Up 2" atopic dermatitis
C17: Phase III "LEVEL UP" vs. dupilumab atopic dermatitis
C19: Phase III "AD-VISE" atopic dermatitis (real world study)
C20: Phase III "UP-TAINED" atopic dermatitis (real world study)
C22: Crohn's Phase III
C23: SELECT-COMPARE
C24: SELECT-CHOICE
C25: SELET-AXIS 2
C26: Phase III "U-ACHIEVE" UC
C27: Phase III "U-EXCEL" UC
... C34: met PE

Sheet Botox
A1: Main
B2: Brand | C2: Botox, Botox Cosmetic
B3: Generic | C3: OnabotulinumtoxinA
B4: Indication | C4: Forehead lines, frown lines, crow's feet
C5: Masseter muscle prominence approved in China
C6: Platysma bands (jawline/neck) FDA approved 10/18/24
B7: Approval | C7: 33581
B8: MOA | C8: Core botulinum neurotoxin is 150kDa
B9: Competition | C9: Dysport, Xeomin, biosimilars, RVNC, Evolus, Hugel

Sheet Elahere
A1: Main
B2: Brand Name | C2: Elahere
B3: Generic Name | C3: mirvetuximab soravtansine
B4: Indication | C4: FRalpha-positive ovarian cancer
B5: Regulatory | C5: FDA approved 11/14/2022. CHMP positive opinion on MIRASOL
B6: Economics | C6: acquired ImmunoGen
B7: Administration | C7: IV
B8: MOA | C8: FRalpha mab with DM4
B9: Clinical Trials
C10: Phase III "MIRASOL" mirv vs. IC - Fralpha+ prOC
C15: Phase II "PICCOLO" monotherapy FRalpha+ platinum-sensitive OC
C16: 52% ORR, 8.25m DOR
C20: Phase II "SORAYA" n=106 2L+ Fralpha+ prOC
C21: 32% ORR, 6.9mo DOR; 4.8% CR

Sheet Qulipta
A1: Main
B2: Brand | C2: Qulipta
B3: Generic | C3: atogepant
B4: Indication | C4: Migraine
B5: Clinical Trials
C6: Phase III "TEMPLE" vs. topiramate
C7: beat onsafety and efficacy

Sheet emraclidine
A1: Main
B2: Brand
B3: Generic | C3: emraclidine
B4: Indication | C4: Schizophrenia
B5: Economics | C5: acquired Cerevel for this asset
B6: MOA | C6: M4 pam
B7: Clinical Trials
C8: Phase II "EMPOWER-1" schizophrenia
C9: placebo | D9: -13.5
C10: 10mg | D10: -14.7
C11: 30mg | D11: -16.5
C13: Phase II "EMPOWER-2" schizophrenia
C14: placebo | D14: -16.1
C15: 10mg | D15: -18.5
C16: 30mg | D16: -14.2

Sheet Epkinly
A1: Main
B2: Brand | C2: Epkinly, Tepkinly
B3: Generic | C3: epcoritamab
B4: Indication | C4: r/r (3L+) FL
B5: Approval | C5: FDA approval 2024, CHMP positive opinion, EC approval 2024
B6: Administration | C6: subcutaneous
B7: Mechanism | C7: bispecific
B8: Economics | C8: GMAB
B9: Clinical Trials
C10: Phase I/II "EPCORE NHL-1" n=157 r/r FL - NCT03625037
C11: GCT3013-01, single-arm, open-label, monotherapy
C12: 3 median prior therapies
C13: 63% ORR, 39% CR
D14: updated data: 59% ORR, 41% CR with median CR duration 36 months
C16: Phase Ib/II "EPCORE NHL-2" n=44 1L DLBCL - NCT04663347
C17: epcoritamab+R-CHOP had 100% ORR, 87% CR, 83% remain in CR after 2 years
D19: Arm 2: n=111 lenalidomide+rituximab R/R FL
D20: 96% ORR, 87% CR
C22: Phase III "EPCORE FL-1" epcori+ritux+lena vs. ritux+lena - NCT05409066
C23: PE: PFS
C25: NCT05578976
C26: NCT05409066
C27: NCT06191744
C28: NCT06508658

Sheet Vyalev
A1: Main
B2: Brand | C2: Vyalev, fka ABBV-951
B3: Generic | C3: foscarbidopa, foslevodopa
B4: Administration | C4: subcutaneous 24-hour
B5: Indication | C5: Parkinson's
B6: Regulatory | C6: FDA approval 10/17/2024

Sheet Venclexta
A1: Main
B2: Brand | C2: Venclexta
B3: Generic | C3: venetoclax
B4: Indication | C4: Chronic Lymphocytic Leukemia, Acute Myeloid Leukemia
B5: MOA | C5: Bcl-2 inhibitor
B6: Economics | C6: Roche
B7: Administration | C7: oral
B8: Regulatory | C8: NDA 208573 approved 4/11/2016
B9: Clinical Trials
C11: Phase III "VERONA" 1L high-risk MDS with azacitidine
C12: PE: OS failed
C16: Phase III "AMPLIFY" Venclexta + acalabrutinib 1L CLL
C17: PFS beat chemoimmunotherapy

Sheet tavapadon
A1: Main
B2: Brand
B3: Generic | C3: tavapadon
B4: Indication | C4: early PD
B5: Mechanism | C5: D1/D5 agonist
B6: Regulatory | C6: filing NDA in 2025
B7: Competition | C7: rotigotine, ropinirole, apomorphine, pramipexole
B8: Clinical Trials
C9: Phase III "TEMPO-1" fixed-dose Parkinson's - NCT04201093
C10: MDS-UPDRS Part II+III at week 26 vs. placebo
C11: placebo +1.8, tavapadon -9.7 and -10.2 at week 26
C13: Phase III "TEMPO-2" flexible-dose Parksinon's - NCT04223193
C14: met PE MDS-UPDRS Part II/III
C15: placebo -1.2, tavapadon -10.3, p<0.0001
C18: Phase III TEMPO-3 adjunctive Parkinson's - NCT04542499
C23: TEMPO-4 - NCT04760769
